Workbook

Sheet Synthese
B2: Synthèse des ventes de la pharmacie
B3: Classeur généré par main.py à partir des exports. Dernier jour de données : 08/10/2019.
B5: Début des données | D5: Dernier mois complet | F5: Jours analysés | H5: Groupes suivis
B6: 41641 | D6: 43709 | F6: 2098 | H6: 8
B8: Ce qu'il faut retenir
B9: • Groupe le plus saisonnier : Antihistaminiques (R06), pic en mai (indice 176, 100 = mois moyen) et creux en décembre (indice 51).
B10: • Groupe le plus régulier sur l'année : Anti-inflammatoires (type diclofénac) (M01AB), indices mensuels entre 93 et 107.
B11: • Jour le plus chargé tous groupes confondus : samedi (indice 106) ; le plus calme : dimanche (indice 94).
B12: • Tendance 2014 à 2018 : plus forte hausse pour Asthme et BPCO (+21.2% par an), plus forte baisse pour Antalgiques salicylés (type aspirine) (-8.5% par an).
B13: • Environnement (donnée publique) : à compléter.
B14: • Structure des ventes : tendance + saisonnalité pour 3, tendance seule pour 2, saisonnalité seule pour 2, ni l'une ni l'autre pour 1 groupe(s). Prévision de octobre 2019 : fiable pour 6 groupe(s) sur 8 (erreur moyenne sous 20% sur 24 mois de test) : M01AB, M01AE, N02BA, N02BE, N05B, R06. Un modèle fait mieux qu'une règle naïve pour 5 groupe(s). Détail dans la feuille Prevision.
B16: Les groupes en un coup d'œil
B17: Libellé | C17: Code | D17: Part du volume | E17: Évolution par an (2014 à 2018) | F17: Mois de pic | G17: Mois creux | H17: Jour le plus fort | I17: Variabilité (CV) | J17: Structure détectée | K17: Prévisible ?
B18: Anti-inflammatoires (type diclofénac) | C18: M01AB | D18: 0.083026536 | E18: 0.056114242 | F18: Août | G18: Juin | H18: Samedi | I18: 0.53292447 | J18: Tendance seule | K18: Oui
B19: Anti-inflammatoires (type ibuprofène) | C19: M01AE | D19: 0.064476482 | E19: 0.025176825 | F19: Janv. | G19: Juin | H19: Dimanche | I19: 0.53606274 | J19: Saisonnalité seule | K19: Oui
B20: Antalgiques salicylés (type aspirine) | C20: N02BA | D20: 0.063508276 | E20: -0.085300816 | F20: Févr. | G20: Sept. | H20: Mardi | I20: 0.60170343 | J20: Tendance + saisonnalité | K20: Oui, une règle simple suffit
B21: Antalgiques (type paracétamol) | C21: N02BE | D21: 0.49643862 | E21: 0.053854108 | F21: Janv. | G21: Juil. | H21: Dimanche | I21: 0.52038851 | J21: Saisonnalité seule | K21: Oui
B22: Anxiolytiques | C22: N05B | D22: 0.1440344 | E22: -0.067219566 | F22: Janv. | G22: Mai | H22: Mercredi | I22: 0.62644869 | J22: Tendance seule | K22: Oui
B23: Hypnotiques et sédatifs | C23: N05C | D23: 0.0096556722 | E23: -0.030687979 | F23: Janv. | G23: Avr. | H23: Vendredi | I23: 1.8513001 | J23: Ni l'une ni l'autre | K23: Non
B24: Asthme et BPCO | C24: R03 | D24: 0.091022073 | E24: 0.211559 | F24: Déc. | G24: Juil. | H24: Lundi | I24: 1.1633451 | J24: Tendance + saisonnalité | K24: Non
B25: Antihistaminiques | C25: R06 | D25: 0.047837947 | E25: 0.10450179 | F25: Mai | G25: Déc. | H25: Samedi | I25: 0.82521177 | J25: Tendance + saisonnalité | K25: Oui
B27: Saisonnalité : indice par mois (100 = mois moyen du groupe, à nombre de jours égal)
B28: Groupe | C28: Janv. | D28: Févr. | E28: Mars | F28: Avr. | G28: Mai | H28: Juin | I28: Juil. | J28: Août | K28: Sept. | L28: Oct. | M28: Nov. | N28: Déc.
B29: Anti-inflammatoires (type diclofénac) (M01AB) | C29: 104 | D29: 97 | E29: 97 | F29: 103 | G29: 96 | H29: 93 | I29: 102 | J29: 107 | K29: 98 | L29: 97 | M29: 103 | N29: 103
B30: Anti-inflammatoires (type ibuprofène) (M01AE) | C30: 118 | D30: 118 | E30: 98 | F30: 94 | G30: 94 | H30: 90 | I30: 95 | J30: 92 | K30: 100 | L30: 98 | M30: 96 | N30: 106
B31: Antalgiques salicylés (type aspirine) (N02BA) | C31: 115 | D31: 121 | E31: 102 | F31: 97 | G31: 96 | H31: 96 | I31: 89 | J31: 89 | K31: 86 | L31: 104 | M31: 107 | N31: 98
B32: Antalgiques (type paracétamol) (N02BE) | C32: 143 | D32: 118 | E32: 97 | F32: 87 | G32: 75 | H32: 67 | I32: 63 | J32: 67 | K32: 104 | L32: 138 | M32: 106 | N32: 135
B33: Anxiolytiques (N05B) | C33: 116 | D33: 100 | E33: 93 | F33: 91 | G33: 85 | H33: 89 | I33: 94 | J33: 103 | K33: 104 | L33: 106 | M33: 105 | N33: 113
B34: Hypnotiques et sédatifs (N05C) | C34: 127 | D34: 91 | E34: 105 | F34: 81 | G34: 103 | H34: 99 | I34: 81 | J34: 103 | K34: 88 | L34: 85 | M34: 114 | N34: 123
B35: Asthme et BPCO (R03) | C35: 126 | D35: 120 | E35: 111 | F35: 103 | G35: 89 | H35: 77 | I35: 52 | J35: 55 | K35: 78 | L35: 130 | M35: 110 | N35: 148
B36: Antihistaminiques (R06) | C36: 56 | D36: 58 | E36: 111 | F36: 171 | G36: 176 | H36: 154 | I36: 117 | J36: 94 | K36: 89 | L36: 69 | M36: 55 | N36: 51
B58: Limites : les quantités sont celles du logiciel de caisse, dont l'unité n'est pas documentée, et l'export ne contient aucun prix. Cette analyse porte donc sur des volumes, pas sur un chiffre d'affaires ni une marge. Les volumes de deux groupes différents ne sont pas directement comparables. Écart maximal constaté entre les quatre exports : 2.99 % (détail dans la feuille Etat_donnees).

Sheet Outil
B2: Ventes par groupe et par période
B3: Modifiez uniquement les cases jaunes. Pour un seul jour, mettez la même date en début et en fin.
B5: Date de début | C5: 43709 | D5: =IF($C$5>$C$6,"La date de début est après la date de fin.","")
B6: Date de fin | C6: 43738 | E6: Données disponibles du 02/01/2014 au 08/10/2019.
B7: Jours avec données | C7: =COUNTIFS(Donnees!$A$2:$A$2107,">="&$C$5,Donnees!$A$2:$A$2107,"<="&$C$6) -> 30 | D7: =IF(AND($C$5<=$C$6,$C$7=0),"Aucune donnée sur cette période.","")
B10: Code | C10: Groupe | D10: Afficher | E10: Total sur la période | F10: Moyenne par jour | G10: Maximum sur un jour | H10: Moyenne habituelle par jour | I10: Écart à l'habitude | AA10: Mois | AB10: Ventes des groupes affichés
B11: M01AB | C11: Anti-inflammatoires (type diclofénac) | D11: Oui | E11: =IF($D11="Oui",SUMIFS(Donnees!$B$2:$B$2107,Donnees!$A$2:$A$2107,">="&$C$5,Donnees!$A$2:$A$2107,"<="&$C$6),"") -> 161.07 | F11: =IF(AND($D11="Oui",$C$7>0),E11/$C$7,"") -> 5.369 | G11: =IF(AND($D11="Oui",$C$7>0),_xlfn.MAXIFS(Donnees!$B$2:$B$2107,Donnees!$A$2:$A$2107,">="&$C$5,Donnees!$A$2:$A$2107,"<="&$C$6),"") -> 10.68 | H11: =IF($D11="Oui",AVERAGE(Donnees!$B$2:$B$2107),"") -> 5.0921154 | I11: =IF(AND($D11="Oui",$C$7>0),F11/H11-1,"") -> 0.054375165 | AA11: 41640 | AB11: =IF(AND(EOMONTH($AA11,0)>=$C$5,$AA11<=$C$6),($D$11="Oui")*SUMIFS(Donnees!$B$2:$B$2107,Donnees!$A$2:$A$2107,">="&MAX($AA11,$C$5),Donnees!$A$2:$A$2107,"<="&MIN(EOMONTH($AA11,0),$C$6))+($D$12="Oui")*SUMIFS(Donnees!$C$2:$C$2107,Donnees!$A$2:$A$2107,">="&MAX($AA11,$C$5),Donnees!$A$2:$A$2107,"<="&MIN(EOMONTH($AA11,0),$C$6))+($D$13="Oui")*SUMIFS(Donnees!$D$2:$D$2107,Donnees!$A$2:$A$2107,">="&MAX($AA11,$C$5),Donnees!$A$2:$A$2107,"<="&MIN(EOMONTH($AA11,0),$C$6))+($D$14="Oui")*SUMIFS(Donnees!$E$2:$E$2107,Donnees!$A$2:$A$2107,">="&MAX($AA11,$C$5),Donnees!$A$2:$A$2107,"<="&MIN(EOMONTH($AA11,0),$C$6))+($D$15="Oui")*SUMIFS(Donnees!$F$2:$F$2107,Donnees!$A$2:$A$2107,">="&MAX($AA11,$C$5),Donnees!$A$2:$A$2107,"<="&MIN(EOMONTH($AA11,0),$C$6))+($D$16="Oui")*SUMIFS(Donnees!$G$2:$G$2107,Donnees!$A$2:$A$2107,">="&MAX($AA11,$C$5),Donnees!$A$2:$A$2107,"<="&MIN(EOMONTH($AA11,0),$C$6))+($D$17="Oui")*SUMIFS(Donnees!$H$2:$H$2107,Donnees!$A$2:$A$2107,">="&MAX($AA11,$C$5),Donnees!$A$2:$A$2107,"<="&MIN(EOMONTH($AA11,0),$C$6))+($D$18="Oui")*SUMIFS(Donnees!$I$2:$I$2107,Donnees!$A$2:$A$2107,">="&MAX($AA11,$C$5),Donnees!$A$2:$A$2107,"<="&MIN(EOMONTH($AA11,0),$C$6)),NA()) -> #N/A
B12: M01AE | C12: Anti-inflammatoires (type ibuprofène) | D12: Oui | E12: =IF($D12="Oui",SUMIFS(Donnees!$C$2:$C$2107,Donnees!$A$2:$A$2107,">="&$C$5,Donnees!$A$2:$A$2107,"<="&$C$6),"") -> 111.437 | F12: =IF(AND($D12="Oui",$C$7>0),E12/$C$7,"") -> 3.7145667 | G12: =IF(AND($D12="Oui",$C$7>0),_xlfn.MAXIFS(Donnees!$C$2:$C$2107,Donnees!$A$2:$A$2107,">="&$C$5,Donnees!$A$2:$A$2107,"<="&$C$6),"") -> 9.53 | H12: =IF($D12="Oui",AVERAGE(Donnees!$C$2:$C$2107),"") -> 3.9557688 | I12: =IF(AND($D12="Oui",$C$7>0),F12/H12-1,"") -> -0.06097477 | AA12: 41671 | AB12: =IF(AND(EOMONTH($AA12,0)>=$C$5,$AA12<=$C$6),($D$11="Oui")*SUMIFS(Donnees!$B$2:$B$2107,Donnees!$A$2:$A$2107,">="&MAX($AA12,$C$5),Donnees!$A$2:$A$2107,"<="&MIN(EOMONTH($AA12,0),$C$6))+($D$12="Oui")*SUMIFS(Donnees!$C$2:$C$2107,Donnees!$A$2:$A$2107,">="&MAX($AA12,$C$5),Donnees!$A$2:$A$2107,"<="&MIN(EOMONTH($AA12,0),$C$6))+($D$13="Oui")*SUMIFS(Donnees!$D$2:$D$2107,Donnees!$A$2:$A$2107,">="&MAX($AA12,$C$5),Donnees!$A$2:$A$2107,"<="&MIN(EOMONTH($AA12,0),$C$6))+($D$14="Oui")*SUMIFS(Donnees!$E$2:$E$2107,Donnees!$A$2:$A$2107,">="&MAX($AA12,$C$5),Donnees!$A$2:$A$2107,"<="&MIN(EOMONTH($AA12,0),$C$6))+($D$15="Oui")*SUMIFS(Donnees!$F$2:$F$2107,Donnees!$A$2:$A$2107,">="&MAX($AA12,$C$5),Donnees!$A$2:$A$2107,"<="&MIN(EOMONTH($AA12,0),$C$6))+($D$16="Oui")*SUMIFS(Donnees!$G$2:$G$2107,Donnees!$A$2:$A$2107,">="&MAX($AA12,$C$5),Donnees!$A$2:$A$2107,"<="&MIN(EOMONTH($AA12,0),$C$6))+($D$17="Oui")*SUMIFS(Donnees!$H$2:$H$2107,Donnees!$A$2:$A$2107,">="&MAX($AA12,$C$5),Donnees!$A$2:$A$2107,"<="&MIN(EOMONTH($AA12,0),$C$6))+($D$18="Oui")*SUMIFS(Donnees!$I$2:$I$2107,Donnees!$A$2:$A$2107,">="&MAX($AA12,$C$5),Donnees!$A$2:$A$2107,"<="&MIN(EOMONTH($AA12,0),$C$6)),NA()) -> #N/A
B13: N02BA | C13: Antalgiques salicylés (type aspirine) | D13: Oui | E13: =IF($D13="Oui",SUMIFS(Donnees!$D$2:$D$2107,Donnees!$A$2:$A$2107,">="&$C$5,Donnees!$A$2:$A$2107,"<="&$C$6),"") -> 93.5 | F13: =IF(AND($D13="Oui",$C$7>0),E13/$C$7,"") -> 3.1166667 | G13: =IF(AND($D13="Oui",$C$7>0),_xlfn.MAXIFS(Donnees!$D$2:$D$2107,Donnees!$A$2:$A$2107,">="&$C$5,Donnees!$A$2:$A$2107,"<="&$C$6),"") -> 7 | H13: =IF($D13="Oui",AVERAGE(Donnees!$D$2:$D$2107),"") -> 3.8887273 | I13: =IF(AND($D13="Oui",$C$7>0),F13/H13-1,"") -> -0.19853812 | AA13: 41699 | AB13: =IF(AND(EOMONTH($AA13,0)>=$C$5,$AA13<=$C$6),($D$11="Oui")*SUMIFS(Donnees!$B$2:$B$2107,Donnees!$A$2:$A$2107,">="&MAX($AA13,$C$5),Donnees!$A$2:$A$2107,"<="&MIN(EOMONTH($AA13,0),$C$6))+($D$12="Oui")*SUMIFS(Donnees!$C$2:$C$2107,Donnees!$A$2:$A$2107,">="&MAX($AA13,$C$5),Donnees!$A$2:$A$2107,"<="&MIN(EOMONTH($AA13,0),$C$6))+($D$13="Oui")*SUMIFS(Donnees!$D$2:$D$2107,Donnees!$A$2:$A$2107,">="&MAX($AA13,$C$5),Donnees!$A$2:$A$2107,"<="&MIN(EOMONTH($AA13,0),$C$6))+($D$14="Oui")*SUMIFS(Donnees!$E$2:$E$2107,Donnees!$A$2:$A$2107,">="&MAX($AA13,$C$5),Donnees!$A$2:$A$2107,"<="&MIN(EOMONTH($AA13,0),$C$6))+($D$15="Oui")*SUMIFS(Donnees!$F$2:$F$2107,Donnees!$A$2:$A$2107,">="&MAX($AA13,$C$5),Donnees!$A$2:$A$2107,"<="&MIN(EOMONTH($AA13,0),$C$6))+($D$16="Oui")*SUMIFS(Donnees!$G$2:$G$2107,Donnees!$A$2:$A$2107,">="&MAX($AA13,$C$5),Donnees!$A$2:$A$2107,"<="&MIN(EOMONTH($AA13,0),$C$6))+($D$17="Oui")*SUMIFS(Donnees!$H$2:$H$2107,Donnees!$A$2:$A$2107,">="&MAX($AA13,$C$5),Donnees!$A$2:$A$2107,"<="&MIN(EOMONTH($AA13,0),$C$6))+($D$18="Oui")*SUMIFS(Donnees!$I$2:$I$2107,Donnees!$A$2:$A$2107,">="&MAX($AA13,$C$5),Donnees!$A$2:$A$2107,"<="&MIN(EOMONTH($AA13,0),$C$6)),NA()) -> #N/A
B14: N02BE | C14: Antalgiques (type paracétamol) | D14: Oui | E14: =IF($D14="Oui",SUMIFS(Donnees!$E$2:$E$2107,Donnees!$A$2:$A$2107,">="&$C$5,Donnees!$A$2:$A$2107,"<="&$C$6),"") -> 984.48 | F14: =IF(AND($D14="Oui",$C$7>0),E14/$C$7,"") -> 32.816 | G14: =IF(AND($D14="Oui",$C$7>0),_xlfn.MAXIFS(Donnees!$E$2:$E$2107,Donnees!$A$2:$A$2107,">="&$C$5,Donnees!$A$2:$A$2107,"<="&$C$6),"") -> 67.8 | H14: =IF($D14="Oui",AVERAGE(Donnees!$E$2:$E$2107),"") -> 30.46134 | I14: =IF(AND($D14="Oui",$C$7>0),F14/H14-1,"") -> 0.077299966 | AA14: 41730 | AB14: =IF(AND(EOMONTH($AA14,0)>=$C$5,$AA14<=$C$6),($D$11="Oui")*SUMIFS(Donnees!$B$2:$B$2107,Donnees!$A$2:$A$2107,">="&MAX($AA14,$C$5),Donnees!$A$2:$A$2107,"<="&MIN(EOMONTH($AA14,0),$C$6))+($D$12="Oui")*SUMIFS(Donnees!$C$2:$C$2107,Donnees!$A$2:$A$2107,">="&MAX($AA14,$C$5),Donnees!$A$2:$A$2107,"<="&MIN(EOMONTH($AA14,0),$C$6))+($D$13="Oui")*SUMIFS(Donnees!$D$2:$D$2107,Donnees!$A$2:$A$2107,">="&MAX($AA14,$C$5),Donnees!$A$2:$A$2107,"<="&MIN(EOMONTH($AA14,0),$C$6))+($D$14="Oui")*SUMIFS(Donnees!$E$2:$E$2107,Donnees!$A$2:$A$2107,">="&MAX($AA14,$C$5),Donnees!$A$2:$A$2107,"<="&MIN(EOMONTH($AA14,0),$C$6))+($D$15="Oui")*SUMIFS(Donnees!$F$2:$F$2107,Donnees!$A$2:$A$2107,">="&MAX($AA14,$C$5),Donnees!$A$2:$A$2107,"<="&MIN(EOMONTH($AA14,0),$C$6))+($D$16="Oui")*SUMIFS(Donnees!$G$2:$G$2107,Donnees!$A$2:$A$2107,">="&MAX($AA14,$C$5),Donnees!$A$2:$A$2107,"<="&MIN(EOMONTH($AA14,0),$C$6))+($D$17="Oui")*SUMIFS(Donnees!$H$2:$H$2107,Donnees!$A$2:$A$2107,">="&MAX($AA14,$C$5),Donnees!$A$2:$A$2107,"<="&MIN(EOMONTH($AA14,0),$C$6))+($D$18="Oui")*SUMIFS(Donnees!$I$2:$I$2107,Donnees!$A$2:$A$2107,">="&MAX($AA14,$C$5),Donnees!$A$2:$A$2107,"<="&MIN(EOMONTH($AA14,0),$C$6)),NA()) -> #N/A
B15: N05B | C15: Anxiolytiques | D15: Oui | E15: =IF($D15="Oui",SUMIFS(Donnees!$F$2:$F$2107,Donnees!$A$2:$A$2107,">="&$C$5,Donnees!$A$2:$A$2107,"<="&$C$6),"") -> 227.8 | F15: =IF(AND($D15="Oui",$C$7>0),E15/$C$7,"") -> 7.5933333 | G15: =IF(AND($D15="Oui",$C$7>0),_xlfn.MAXIFS(Donnees!$F$2:$F$2107,Donnees!$A$2:$A$2107,">="&$C$5,Donnees!$A$2:$A$2107,"<="&$C$6),"") -> 17 | H15: =IF($D15="Oui",AVERAGE(Donnees!$F$2:$F$2107),"") -> 8.8380856 | I15: =IF(AND($D15="Oui",$C$7>0),F15/H15-1,"") -> -0.14083958 | AA15: 41760 | AB15: =IF(AND(EOMONTH($AA15,0)>=$C$5,$AA15<=$C$6),($D$11="Oui")*SUMIFS(Donnees!$B$2:$B$2107,Donnees!$A$2:$A$2107,">="&MAX($AA15,$C$5),Donnees!$A$2:$A$2107,"<="&MIN(EOMONTH($AA15,0),$C$6))+($D$12="Oui")*SUMIFS(Donnees!$C$2:$C$2107,Donnees!$A$2:$A$2107,">="&MAX($AA15,$C$5),Donnees!$A$2:$A$2107,"<="&MIN(EOMONTH($AA15,0),$C$6))+($D$13="Oui")*SUMIFS(Donnees!$D$2:$D$2107,Donnees!$A$2:$A$2107,">="&MAX($AA15,$C$5),Donnees!$A$2:$A$2107,"<="&MIN(EOMONTH($AA15,0),$C$6))+($D$14="Oui")*SUMIFS(Donnees!$E$2:$E$2107,Donnees!$A$2:$A$2107,">="&MAX($AA15,$C$5),Donnees!$A$2:$A$2107,"<="&MIN(EOMONTH($AA15,0),$C$6))+($D$15="Oui")*SUMIFS(Donnees!$F$2:$F$2107,Donnees!$A$2:$A$2107,">="&MAX($AA15,$C$5),Donnees!$A$2:$A$2107,"<="&MIN(EOMONTH($AA15,0),$C$6))+($D$16="Oui")*SUMIFS(Donnees!$G$2:$G$2107,Donnees!$A$2:$A$2107,">="&MAX($AA15,$C$5),Donnees!$A$2:$A$2107,"<="&MIN(EOMONTH($AA15,0),$C$6))+($D$17="Oui")*SUMIFS(Donnees!$H$2:$H$2107,Donnees!$A$2:$A$2107,">="&MAX($AA15,$C$5),Donnees!$A$2:$A$2107,"<="&MIN(EOMONTH($AA15,0),$C$6))+($D$18="Oui")*SUMIFS(Donnees!$I$2:$I$2107,Donnees!$A$2:$A$2107,">="&MAX($AA15,$C$5),Donnees!$A$2:$A$2107,"<="&MIN(EOMONTH($AA15,0),$C$6)),NA()) -> #N/A
B16: N05C | C16: Hypnotiques et sédatifs | D16: Oui | E16: =IF($D16="Oui",SUMIFS(Donnees!$G$2:$G$2107,Donnees!$A$2:$A$2107,">="&$C$5,Donnees!$A$2:$A$2107,"<="&$C$6),"") -> 16 | F16: =IF(AND($D16="Oui",$C$7>0),E16/$C$7,"") -> 0.53333333 | G16: =IF(AND($D16="Oui",$C$7>0),_xlfn.MAXIFS(Donnees!$G$2:$G$2107,Donnees!$A$2:$A$2107,">="&$C$5,Donnees!$A$2:$A$2107,"<="&$C$6),"") -> 3 | H16: =IF($D16="Oui",AVERAGE(Donnees!$G$2:$G$2107),"") -> 0.59306743 | I16: =IF(AND($D16="Oui",$C$7>0),F16/H16-1,"") -> -0.10072058 | AA16: 41791 | AB16: =IF(AND(EOMONTH($AA16,0)>=$C$5,$AA16<=$C$6),($D$11="Oui")*SUMIFS(Donnees!$B$2:$B$2107,Donnees!$A$2:$A$2107,">="&MAX($AA16,$C$5),Donnees!$A$2:$A$2107,"<="&MIN(EOMONTH($AA16,0),$C$6))+($D$12="Oui")*SUMIFS(Donnees!$C$2:$C$2107,Donnees!$A$2:$A$2107,">="&MAX($AA16,$C$5),Donnees!$A$2:$A$2107,"<="&MIN(EOMONTH($AA16,0),$C$6))+($D$13="Oui")*SUMIFS(Donnees!$D$2:$D$2107,Donnees!$A$2:$A$2107,">="&MAX($AA16,$C$5),Donnees!$A$2:$A$2107,"<="&MIN(EOMONTH($AA16,0),$C$6))+($D$14="Oui")*SUMIFS(Donnees!$E$2:$E$2107,Donnees!$A$2:$A$2107,">="&MAX($AA16,$C$5),Donnees!$A$2:$A$2107,"<="&MIN(EOMONTH($AA16,0),$C$6))+($D$15="Oui")*SUMIFS(Donnees!$F$2:$F$2107,Donnees!$A$2:$A$2107,">="&MAX($AA16,$C$5),Donnees!$A$2:$A$2107,"<="&MIN(EOMONTH($AA16,0),$C$6))+($D$16="Oui")*SUMIFS(Donnees!$G$2:$G$2107,Donnees!$A$2:$A$2107,">="&MAX($AA16,$C$5),Donnees!$A$2:$A$2107,"<="&MIN(EOMONTH($AA16,0),$C$6))+($D$17="Oui")*SUMIFS(Donnees!$H$2:$H$2107,Donnees!$A$2:$A$2107,">="&MAX($AA16,$C$5),Donnees!$A$2:$A$2107,"<="&MIN(EOMONTH($AA16,0),$C$6))+($D$18="Oui")*SUMIFS(Donnees!$I$2:$I$2107,Donnees!$A$2:$A$2107,">="&MAX($AA16,$C$5),Donnees!$A$2:$A$2107,"<="&MIN(EOMONTH($AA16,0),$C$6)),NA()) -> #N/A
B17: R03 | C17: Asthme et BPCO | D17: Oui | E17: =IF($D17="Oui",SUMIFS(Donnees!$H$2:$H$2107,Donnees!$A$2:$A$2107,">="&$C$5,Donnees!$A$2:$A$2107,"<="&$C$6),"") -> 121.41667 | F17: =IF(AND($D17="Oui",$C$7>0),E17/$C$7,"") -> 4.0472222 | G17: =IF(AND($D17="Oui",$C$7>0),_xlfn.MAXIFS(Donnees!$H$2:$H$2107,Donnees!$A$2:$A$2107,">="&$C$5,Donnees!$A$2:$A$2107,"<="&$C$6),"") -> 31 | H17: =IF($D17="Oui",AVERAGE(Donnees!$H$2:$H$2107),"") -> 5.5769626 | I17: =IF(AND($D17="Oui",$C$7>0),F17/H17-1,"") -> -0.27429634 | AA17: 41821 | AB17: =IF(AND(EOMONTH($AA17,0)>=$C$5,$AA17<=$C$6),($D$11="Oui")*SUMIFS(Donnees!$B$2:$B$2107,Donnees!$A$2:$A$2107,">="&MAX($AA17,$C$5),Donnees!$A$2:$A$2107,"<="&MIN(EOMONTH($AA17,0),$C$6))+($D$12="Oui")*SUMIFS(Donnees!$C$2:$C$2107,Donnees!$A$2:$A$2107,">="&MAX($AA17,$C$5),Donnees!$A$2:$A$2107,"<="&MIN(EOMONTH($AA17,0),$C$6))+($D$13="Oui")*SUMIFS(Donnees!$D$2:$D$2107,Donnees!$A$2:$A$2107,">="&MAX($AA17,$C$5),Donnees!$A$2:$A$2107,"<="&MIN(EOMONTH($AA17,0),$C$6))+($D$14="Oui")*SUMIFS(Donnees!$E$2:$E$2107,Donnees!$A$2:$A$2107,">="&MAX($AA17,$C$5),Donnees!$A$2:$A$2107,"<="&MIN(EOMONTH($AA17,0),$C$6))+($D$15="Oui")*SUMIFS(Donnees!$F$2:$F$2107,Donnees!$A$2:$A$2107,">="&MAX($AA17,$C$5),Donnees!$A$2:$A$2107,"<="&MIN(EOMONTH($AA17,0),$C$6))+($D$16="Oui")*SUMIFS(Donnees!$G$2:$G$2107,Donnees!$A$2:$A$2107,">="&MAX($AA17,$C$5),Donnees!$A$2:$A$2107,"<="&MIN(EOMONTH($AA17,0),$C$6))+($D$17="Oui")*SUMIFS(Donnees!$H$2:$H$2107,Donnees!$A$2:$A$2107,">="&MAX($AA17,$C$5),Donnees!$A$2:$A$2107,"<="&MIN(EOMONTH($AA17,0),$C$6))+($D$18="Oui")*SUMIFS(Donnees!$I$2:$I$2107,Donnees!$A$2:$A$2107,">="&MAX($AA17,$C$5),Donnees!$A$2:$A$2107,"<="&MIN(EOMONTH($AA17,0),$C$6)),NA()) -> #N/A
B18: R06 | C18: Antihistaminiques | D18: Oui | E18: =IF($D18="Oui",SUMIFS(Donnees!$I$2:$I$2107,Donnees!$A$2:$A$2107,">="&$C$5,Donnees!$A$2:$A$2107,"<="&$C$6),"") -> 109.1 | F18: =IF(AND($D18="Oui",$C$7>0),E18/$C$7,"") -> 3.6366667 | G18: =IF(AND($D18="Oui",$C$7>0),_xlfn.MAXIFS(Donnees!$I$2:$I$2107,Donnees!$A$2:$A$2107,">="&$C$5,Donnees!$A$2:$A$2107,"<="&$C$6),"") -> 10 | H18: =IF($D18="Oui",AVERAGE(Donnees!$I$2:$I$2107),"") -> 2.9271035 | I18: =IF(AND($D18="Oui",$C$7>0),F18/H18-1,"") -> 0.24241136 | AA18: 41852 | AB18: =IF(AND(EOMONTH($AA18,0)>=$C$5,$AA18<=$C$6),($D$11="Oui")*SUMIFS(Donnees!$B$2:$B$2107,Donnees!$A$2:$A$2107,">="&MAX($AA18,$C$5),Donnees!$A$2:$A$2107,"<="&MIN(EOMONTH($AA18,0),$C$6))+($D$12="Oui")*SUMIFS(Donnees!$C$2:$C$2107,Donnees!$A$2:$A$2107,">="&MAX($AA18,$C$5),Donnees!$A$2:$A$2107,"<="&MIN(EOMONTH($AA18,0),$C$6))+($D$13="Oui")*SUMIFS(Donnees!$D$2:$D$2107,Donnees!$A$2:$A$2107,">="&MAX($AA18,$C$5),Donnees!$A$2:$A$2107,"<="&MIN(EOMONTH($AA18,0),$C$6))+($D$14="Oui")*SUMIFS(Donnees!$E$2:$E$2107,Donnees!$A$2:$A$2107,">="&MAX($AA18,$C$5),Donnees!$A$2:$A$2107,"<="&MIN(EOMONTH($AA18,0),$C$6))+($D$15="Oui")*SUMIFS(Donnees!$F$2:$F$2107,Donnees!$A$2:$A$2107,">="&MAX($AA18,$C$5),Donnees!$A$2:$A$2107,"<="&MIN(EOMONTH($AA18,0),$C$6))+($D$16="Oui")*SUMIFS(Donnees!$G$2:$G$2107,Donnees!$A$2:$A$2107,">="&MAX($AA18,$C$5),Donnees!$A$2:$A$2107,"<="&MIN(EOMONTH($AA18,0),$C$6))+($D$17="Oui")*SUMIFS(Donnees!$H$2:$H$2107,Donnees!$A$2:$A$2107,">="&MAX($AA18,$C$5),Donnees!$A$2:$A$2107,"<="&MIN(EOMONTH($AA18,0),$C$6))+($D$18="Oui")*SUMIFS(Donnees!$I$2:$I$2107,Donnees!$A$2:$A$2107,">="&MAX($AA18,$C$5),Donnees!$A$2:$A$2107,"<="&MIN(EOMONTH($AA18,0),$C$6)),NA()) -> #N/A
C19: Total des groupes affichés | E19: =SUM(E11:E18) -> 1824.8037 | F19: =IF($C$7>0,E19/$C$7,"") -> 60.826789 | AA19: 41883 | AB19: =IF(AND(EOMONTH($AA19,0)>=$C$5,$AA19<=$C$6),($D$11="Oui")*SUMIFS(Donnees!$B$2:$B$2107,Donnees!$A$2:$A$2107,">="&MAX($AA19,$C$5),Donnees!$A$2:$A$2107,"<="&MIN(EOMONTH($AA19,0),$C$6))+($D$12="Oui")*SUMIFS(Donnees!$C$2:$C$2107,Donnees!$A$2:$A$2107,">="&MAX($AA19,$C$5),Donnees!$A$2:$A$2107,"<="&MIN(EOMONTH($AA19,0),$C$6))+($D$13="Oui")*SUMIFS(Donnees!$D$2:$D$2107,Donnees!$A$2:$A$2107,">="&MAX($AA19,$C$5),Donnees!$A$2:$A$2107,"<="&MIN(EOMONTH($AA19,0),$C$6))+($D$14="Oui")*SUMIFS(Donnees!$E$2:$E$2107,Donnees!$A$2:$A$2107,">="&MAX($AA19,$C$5),Donnees!$A$2:$A$2107,"<="&MIN(EOMONTH($AA19,0),$C$6))+($D$15="Oui")*SUMIFS(Donnees!$F$2:$F$2107,Donnees!$A$2:$A$2107,">="&MAX($AA19,$C$5),Donnees!$A$2:$A$2107,"<="&MIN(EOMONTH($AA19,0),$C$6))+($D$16="Oui")*SUMIFS(Donnees!$G$2:$G$2107,Donnees!$A$2:$A$2107,">="&MAX($AA19,$C$5),Donnees!$A$2:$A$2107,"<="&MIN(EOMONTH($AA19,0),$C$6))+($D$17="Oui")*SUMIFS(Donnees!$H$2:$H$2107,Donnees!$A$2:$A$2107,">="&MAX($AA19,$C$5),Donnees!$A$2:$A$2107,"<="&MIN(EOMONTH($AA19,0),$C$6))+($D$18="Oui")*SUMIFS(Donnees!$I$2:$I$2107,Donnees!$A$2:$A$2107,">="&MAX($AA19,$C$5),Donnees!$A$2:$A$2107,"<="&MIN(EOMONTH($AA19,0),$C$6)),NA()) -> #N/A
AA20: 41913 | AB20: =IF(AND(EOMONTH($AA20,0)>=$C$5,$AA20<=$C$6),($D$11="Oui")*SUMIFS(Donnees!$B$2:$B$2107,Donnees!$A$2:$A$2107,">="&MAX($AA20,$C$5),Donnees!$A$2:$A$2107,"<="&MIN(EOMONTH($AA20,0),$C$6))+($D$12="Oui")*SUMIFS(Donnees!$C$2:$C$2107,Donnees!$A$2:$A$2107,">="&MAX($AA20,$C$5),Donnees!$A$2:$A$2107,"<="&MIN(EOMONTH($AA20,0),$C$6))+($D$13="Oui")*SUMIFS(Donnees!$D$2:$D$2107,Donnees!$A$2:$A$2107,">="&MAX($AA20,$C$5),Donnees!$A$2:$A$2107,"<="&MIN(EOMONTH($AA20,0),$C$6))+($D$14="Oui")*SUMIFS(Donnees!$E$2:$E$2107,Donnees!$A$2:$A$2107,">="&MAX($AA20,$C$5),Donnees!$A$2:$A$2107,"<="&MIN(EOMONTH($AA20,0),$C$6))+($D$15="Oui")*SUMIFS(Donnees!$F$2:$F$2107,Donnees!$A$2:$A$2107,">="&MAX($AA20,$C$5),Donnees!$A$2:$A$2107,"<="&MIN(EOMONTH($AA20,0),$C$6))+($D$16="Oui")*SUMIFS(Donnees!$G$2:$G$2107,Donnees!$A$2:$A$2107,">="&MAX($AA20,$C$5),Donnees!$A$2:$A$2107,"<="&MIN(EOMONTH($AA20,0),$C$6))+($D$17="Oui")*SUMIFS(Donnees!$H$2:$H$2107,Donnees!$A$2:$A$2107,">="&MAX($AA20,$C$5),Donnees!$A$2:$A$2107,"<="&MIN(EOMONTH($AA20,0),$C$6))+($D$18="Oui")*SUMIFS(Donnees!$I$2:$I$2107,Donnees!$A$2:$A$2107,">="&MAX($AA20,$C$5),Donnees!$A$2:$A$2107,"<="&MIN(EOMONTH($AA20,0),$C$6)),NA()) -> #N/A
AA21: 41944 | AB21: =IF(AND(EOMONTH($AA21,0)>=$C$5,$AA21<=$C$6),($D$11="Oui")*SUMIFS(Donnees!$B$2:$B$2107,Donnees!$A$2:$A$2107,">="&MAX($AA21,$C$5),Donnees!$A$2:$A$2107,"<="&MIN(EOMONTH($AA21,0),$C$6))+($D$12="Oui")*SUMIFS(Donnees!$C$2:$C$2107,Donnees!$A$2:$A$2107,">="&MAX($AA21,$C$5),Donnees!$A$2:$A$2107,"<="&MIN(EOMONTH($AA21,0),$C$6))+($D$13="Oui")*SUMIFS(Donnees!$D$2:$D$2107,Donnees!$A$2:$A$2107,">="&MAX($AA21,$C$5),Donnees!$A$2:$A$2107,"<="&MIN(EOMONTH($AA21,0),$C$6))+($D$14="Oui")*SUMIFS(Donnees!$E$2:$E$2107,Donnees!$A$2:$A$2107,">="&MAX($AA21,$C$5),Donnees!$A$2:$A$2107,"<="&MIN(EOMONTH($AA21,0),$C$6))+($D$15="Oui")*SUMIFS(Donnees!$F$2:$F$2107,Donnees!$A$2:$A$2107,">="&MAX($AA21,$C$5),Donnees!$A$2:$A$2107,"<="&MIN(EOMONTH($AA21,0),$C$6))+($D$16="Oui")*SUMIFS(Donnees!$G$2:$G$2107,Donnees!$A$2:$A$2107,">="&MAX($AA21,$C$5),Donnees!$A$2:$A$2107,"<="&MIN(EOMONTH($AA21,0),$C$6))+($D$17="Oui")*SUMIFS(Donnees!$H$2:$H$2107,Donnees!$A$2:$A$2107,">="&MAX($AA21,$C$5),Donnees!$A$2:$A$2107,"<="&MIN(EOMONTH($AA21,0),$C$6))+($D$18="Oui")*SUMIFS(Donnees!$I$2:$I$2107,Donnees!$A$2:$A$2107,">="&MAX($AA21,$C$5),Donnees!$A$2:$A$2107,"<="&MIN(EOMONTH($AA21,0),$C$6)),NA()) -> #N/A
AA22: 41974 | AB22: =IF(AND(EOMONTH($AA22,0)>=$C$5,$AA22<=$C$6),($D$11="Oui")*SUMIFS(Donnees!$B$2:$B$2107,Donnees!$A$2:$A$2107,">="&MAX($AA22,$C$5),Donnees!$A$2:$A$2107,"<="&MIN(EOMONTH($AA22,0),$C$6))+($D$12="Oui")*SUMIFS(Donnees!$C$2:$C$2107,Donnees!$A$2:$A$2107,">="&MAX($AA22,$C$5),Donnees!$A$2:$A$2107,"<="&MIN(EOMONTH($AA22,0),$C$6))+($D$13="Oui")*SUMIFS(Donnees!$D$2:$D$2107,Donnees!$A$2:$A$2107,">="&MAX($AA22,$C$5),Donnees!$A$2:$A$2107,"<="&MIN(EOMONTH($AA22,0),$C$6))+($D$14="Oui")*SUMIFS(Donnees!$E$2:$E$2107,Donnees!$A$2:$A$2107,">="&MAX($AA22,$C$5),Donnees!$A$2:$A$2107,"<="&MIN(EOMONTH($AA22,0),$C$6))+($D$15="Oui")*SUMIFS(Donnees!$F$2:$F$2107,Donnees!$A$2:$A$2107,">="&MAX($AA22,$C$5),Donnees!$A$2:$A$2107,"<="&MIN(EOMONTH($AA22,0),$C$6))+($D$16="Oui")*SUMIFS(Donnees!$G$2:$G$2107,Donnees!$A$2:$A$2107,">="&MAX($AA22,$C$5),Donnees!$A$2:$A$2107,"<="&MIN(EOMONTH($AA22,0),$C$6))+($D$17="Oui")*SUMIFS(Donnees!$H$2:$H$2107,Donnees!$A$2:$A$2107,">="&MAX($AA22,$C$5),Donnees!$A$2:$A$2107,"<="&MIN(EOMONTH($AA22,0),$C$6))+($D$18="Oui")*SUMIFS(Donnees!$I$2:$I$2107,Donnees!$A$2:$A$2107,">="&MAX($AA22,$C$5),Donnees!$A$2:$A$2107,"<="&MIN(EOMONTH($AA22,0),$C$6)),NA()) -> #N/A
AA23: 42005 | AB23: =IF(AND(EOMONTH($AA23,0)>=$C$5,$AA23<=$C$6),($D$11="Oui")*SUMIFS(Donnees!$B$2:$B$2107,Donnees!$A$2:$A$2107,">="&MAX($AA23,$C$5),Donnees!$A$2:$A$2107,"<="&MIN(EOMONTH($AA23,0),$C$6))+($D$12="Oui")*SUMIFS(Donnees!$C$2:$C$2107,Donnees!$A$2:$A$2107,">="&MAX($AA23,$C$5),Donnees!$A$2:$A$2107,"<="&MIN(EOMONTH($AA23,0),$C$6))+($D$13="Oui")*SUMIFS(Donnees!$D$2:$D$2107,Donnees!$A$2:$A$2107,">="&MAX($AA23,$C$5),Donnees!$A$2:$A$2107,"<="&MIN(EOMONTH($AA23,0),$C$6))+($D$14="Oui")*SUMIFS(Donnees!$E$2:$E$2107,Donnees!$A$2:$A$2107,">="&MAX($AA23,$C$5),Donnees!$A$2:$A$2107,"<="&MIN(EOMONTH($AA23,0),$C$6))+($D$15="Oui")*SUMIFS(Donnees!$F$2:$F$2107,Donnees!$A$2:$A$2107,">="&MAX($AA23,$C$5),Donnees!$A$2:$A$2107,"<="&MIN(EOMONTH($AA23,0),$C$6))+($D$16="Oui")*SUMIFS(Donnees!$G$2:$G$2107,Donnees!$A$2:$A$2107,">="&MAX($AA23,$C$5),Donnees!$A$2:$A$2107,"<="&MIN(EOMONTH($AA23,0),$C$6))+($D$17="Oui")*SUMIFS(Donnees!$H$2:$H$2107,Donnees!$A$2:$A$2107,">="&MAX($AA23,$C$5),Donnees!$A$2:$A$2107,"<="&MIN(EOMONTH($AA23,0),$C$6))+($D$18="Oui")*SUMIFS(Donnees!$I$2:$I$2107,Donnees!$A$2:$A$2107,">="&MAX($AA23,$C$5),Donnees!$A$2:$A$2107,"<="&MIN(EOMONTH($AA23,0),$C$6)),NA()) -> #N/A
AA24: 42036 | AB24: =IF(AND(EOMONTH($AA24,0)>=$C$5,$AA24<=$C$6),($D$11="Oui")*SUMIFS(Donnees!$B$2:$B$2107,Donnees!$A$2:$A$2107,">="&MAX($AA24,$C$5),Donnees!$A$2:$A$2107,"<="&MIN(EOMONTH($AA24,0),$C$6))+($D$12="Oui")*SUMIFS(Donnees!$C$2:$C$2107,Donnees!$A$2:$A$2107,">="&MAX($AA24,$C$5),Donnees!$A$2:$A$2107,"<="&MIN(EOMONTH($AA24,0),$C$6))+($D$13="Oui")*SUMIFS(Donnees!$D$2:$D$2107,Donnees!$A$2:$A$2107,">="&MAX($AA24,$C$5),Donnees!$A$2:$A$2107,"<="&MIN(EOMONTH($AA24,0),$C$6))+($D$14="Oui")*SUMIFS(Donnees!$E$2:$E$2107,Donnees!$A$2:$A$2107,">="&MAX($AA24,$C$5),Donnees!$A$2:$A$2107,"<="&MIN(EOMONTH($AA24,0),$C$6))+($D$15="Oui")*SUMIFS(Donnees!$F$2:$F$2107,Donnees!$A$2:$A$2107,">="&MAX($AA24,$C$5),Donnees!$A$2:$A$2107,"<="&MIN(EOMONTH($AA24,0),$C$6))+($D$16="Oui")*SUMIFS(Donnees!$G$2:$G$2107,Donnees!$A$2:$A$2107,">="&MAX($AA24,$C$5),Donnees!$A$2:$A$2107,"<="&MIN(EOMONTH($AA24,0),$C$6))+($D$17="Oui")*SUMIFS(Donnees!$H$2:$H$2107,Donnees!$A$2:$A$2107,">="&MAX($AA24,$C$5),Donnees!$A$2:$A$2107,"<="&MIN(EOMONTH($AA24,0),$C$6))+($D$18="Oui")*SUMIFS(Donnees!$I$2:$I$2107,Donnees!$A$2:$A$2107,">="&MAX($AA24,$C$5),Donnees!$A$2:$A$2107,"<="&MIN(EOMONTH($AA24,0),$C$6)),NA()) -> #N/A
AA25: 42064 | AB25: =IF(AND(EOMONTH($AA25,0)>=$C$5,$AA25<=$C$6),($D$11="Oui")*SUMIFS(Donnees!$B$2:$B$2107,Donnees!$A$2:$A$2107,">="&MAX($AA25,$C$5),Donnees!$A$2:$A$2107,"<="&MIN(EOMONTH($AA25,0),$C$6))+($D$12="Oui")*SUMIFS(Donnees!$C$2:$C$2107,Donnees!$A$2:$A$2107,">="&MAX($AA25,$C$5),Donnees!$A$2:$A$2107,"<="&MIN(EOMONTH($AA25,0),$C$6))+($D$13="Oui")*SUMIFS(Donnees!$D$2:$D$2107,Donnees!$A$2:$A$2107,">="&MAX($AA25,$C$5),Donnees!$A$2:$A$2107,"<="&MIN(EOMONTH($AA25,0),$C$6))+($D$14="Oui")*SUMIFS(Donnees!$E$2:$E$2107,Donnees!$A$2:$A$2107,">="&MAX($AA25,$C$5),Donnees!$A$2:$A$2107,"<="&MIN(EOMONTH($AA25,0),$C$6))+($D$15="Oui")*SUMIFS(Donnees!$F$2:$F$2107,Donnees!$A$2:$A$2107,">="&MAX($AA25,$C$5),Donnees!$A$2:$A$2107,"<="&MIN(EOMONTH($AA25,0),$C$6))+($D$16="Oui")*SUMIFS(Donnees!$G$2:$G$2107,Donnees!$A$2:$A$2107,">="&MAX($AA25,$C$5),Donnees!$A$2:$A$2107,"<="&MIN(EOMONTH($AA25,0),$C$6))+($D$17="Oui")*SUMIFS(Donnees!$H$2:$H$2107,Donnees!$A$2:$A$2107,">="&MAX($AA25,$C$5),Donnees!$A$2:$A$2107,"<="&MIN(EOMONTH($AA25,0),$C$6))+($D$18="Oui")*SUMIFS(Donnees!$I$2:$I$2107,Donnees!$A$2:$A$2107,">="&MAX($AA25,$C$5),Donnees!$A$2:$A$2107,"<="&MIN(EOMONTH($AA25,0),$C$6)),NA()) -> #N/A
AA26: 42095 | AB26: =IF(AND(EOMONTH($AA26,0)>=$C$5,$AA26<=$C$6),($D$11="Oui")*SUMIFS(Donnees!$B$2:$B$2107,Donnees!$A$2:$A$2107,">="&MAX($AA26,$C$5),Donnees!$A$2:$A$2107,"<="&MIN(EOMONTH($AA26,0),$C$6))+($D$12="Oui")*SUMIFS(Donnees!$C$2:$C$2107,Donnees!$A$2:$A$2107,">="&MAX($AA26,$C$5),Donnees!$A$2:$A$2107,"<="&MIN(EOMONTH($AA26,0),$C$6))+($D$13="Oui")*SUMIFS(Donnees!$D$2:$D$2107,Donnees!$A$2:$A$2107,">="&MAX($AA26,$C$5),Donnees!$A$2:$A$2107,"<="&MIN(EOMONTH($AA26,0),$C$6))+($D$14="Oui")*SUMIFS(Donnees!$E$2:$E$2107,Donnees!$A$2:$A$2107,">="&MAX($AA26,$C$5),Donnees!$A$2:$A$2107,"<="&MIN(EOMONTH($AA26,0),$C$6))+($D$15="Oui")*SUMIFS(Donnees!$F$2:$F$2107,Donnees!$A$2:$A$2107,">="&MAX($AA26,$C$5),Donnees!$A$2:$A$2107,"<="&MIN(EOMONTH($AA26,0),$C$6))+($D$16="Oui")*SUMIFS(Donnees!$G$2:$G$2107,Donnees!$A$2:$A$2107,">="&MAX($AA26,$C$5),Donnees!$A$2:$A$2107,"<="&MIN(EOMONTH($AA26,0),$C$6))+($D$17="Oui")*SUMIFS(Donnees!$H$2:$H$2107,Donnees!$A$2:$A$2107,">="&MAX($AA26,$C$5),Donnees!$A$2:$A$2107,"<="&MIN(EOMONTH($AA26,0),$C$6))+($D$18="Oui")*SUMIFS(Donnees!$I$2:$I$2107,Donnees!$A$2:$A$2107,">="&MAX($AA26,$C$5),Donnees!$A$2:$A$2107,"<="&MIN(EOMONTH($AA26,0),$C$6)),NA()) -> #N/A
AA27: 42125 | AB27: =IF(AND(EOMONTH($AA27,0)>=$C$5,$AA27<=$C$6),($D$11="Oui")*SUMIFS(Donnees!$B$2:$B$2107,Donnees!$A$2:$A$2107,">="&MAX($AA27,$C$5),Donnees!$A$2:$A$2107,"<="&MIN(EOMONTH($AA27,0),$C$6))+($D$12="Oui")*SUMIFS(Donnees!$C$2:$C$2107,Donnees!$A$2:$A$2107,">="&MAX($AA27,$C$5),Donnees!$A$2:$A$2107,"<="&MIN(EOMONTH($AA27,0),$C$6))+($D$13="Oui")*SUMIFS(Donnees!$D$2:$D$2107,Donnees!$A$2:$A$2107,">="&MAX($AA27,$C$5),Donnees!$A$2:$A$2107,"<="&MIN(EOMONTH($AA27,0),$C$6))+($D$14="Oui")*SUMIFS(Donnees!$E$2:$E$2107,Donnees!$A$2:$A$2107,">="&MAX($AA27,$C$5),Donnees!$A$2:$A$2107,"<="&MIN(EOMONTH($AA27,0),$C$6))+($D$15="Oui")*SUMIFS(Donnees!$F$2:$F$2107,Donnees!$A$2:$A$2107,">="&MAX($AA27,$C$5),Donnees!$A$2:$A$2107,"<="&MIN(EOMONTH($AA27,0),$C$6))+($D$16="Oui")*SUMIFS(Donnees!$G$2:$G$2107,Donnees!$A$2:$A$2107,">="&MAX($AA27,$C$5),Donnees!$A$2:$A$2107,"<="&MIN(EOMONTH($AA27,0),$C$6))+($D$17="Oui")*SUMIFS(Donnees!$H$2:$H$2107,Donnees!$A$2:$A$2107,">="&MAX($AA27,$C$5),Donnees!$A$2:$A$2107,"<="&MIN(EOMONTH($AA27,0),$C$6))+($D$18="Oui")*SUMIFS(Donnees!$I$2:$I$2107,Donnees!$A$2:$A$2107,">="&MAX($AA27,$C$5),Donnees!$A$2:$A$2107,"<="&MIN(EOMONTH($AA27,0),$C$6)),NA()) -> #N/A
AA28: 42156 | AB28: =IF(AND(EOMONTH($AA28,0)>=$C$5,$AA28<=$C$6),($D$11="Oui")*SUMIFS(Donnees!$B$2:$B$2107,Donnees!$A$2:$A$2107,">="&MAX($AA28,$C$5),Donnees!$A$2:$A$2107,"<="&MIN(EOMONTH($AA28,0),$C$6))+($D$12="Oui")*SUMIFS(Donnees!$C$2:$C$2107,Donnees!$A$2:$A$2107,">="&MAX($AA28,$C$5),Donnees!$A$2:$A$2107,"<="&MIN(EOMONTH($AA28,0),$C$6))+($D$13="Oui")*SUMIFS(Donnees!$D$2:$D$2107,Donnees!$A$2:$A$2107,">="&MAX($AA28,$C$5),Donnees!$A$2:$A$2107,"<="&MIN(EOMONTH($AA28,0),$C$6))+($D$14="Oui")*SUMIFS(Donnees!$E$2:$E$2107,Donnees!$A$2:$A$2107,">="&MAX($AA28,$C$5),Donnees!$A$2:$A$2107,"<="&MIN(EOMONTH($AA28,0),$C$6))+($D$15="Oui")*SUMIFS(Donnees!$F$2:$F$2107,Donnees!$A$2:$A$2107,">="&MAX($AA28,$C$5),Donnees!$A$2:$A$2107,"<="&MIN(EOMONTH($AA28,0),$C$6))+($D$16="Oui")*SUMIFS(Donnees!$G$2:$G$2107,Donnees!$A$2:$A$2107,">="&MAX($AA28,$C$5),Donnees!$A$2:$A$2107,"<="&MIN(EOMONTH($AA28,0),$C$6))+($D$17="Oui")*SUMIFS(Donnees!$H$2:$H$2107,Donnees!$A$2:$A$2107,">="&MAX($AA28,$C$5),Donnees!$A$2:$A$2107,"<="&MIN(EOMONTH($AA28,0),$C$6))+($D$18="Oui")*SUMIFS(Donnees!$I$2:$I$2107,Donnees!$A$2:$A$2107,">="&MAX($AA28,$C$5),Donnees!$A$2:$A$2107,"<="&MIN(EOMONTH($AA28,0),$C$6)),NA()) -> #N/A
AA29: 42186 | AB29: =IF(AND(EOMONTH($AA29,0)>=$C$5,$AA29<=$C$6),($D$11="Oui")*SUMIFS(Donnees!$B$2:$B$2107,Donnees!$A$2:$A$2107,">="&MAX($AA29,$C$5),Donnees!$A$2:$A$2107,"<="&MIN(EOMONTH($AA29,0),$C$6))+($D$12="Oui")*SUMIFS(Donnees!$C$2:$C$2107,Donnees!$A$2:$A$2107,">="&MAX($AA29,$C$5),Donnees!$A$2:$A$2107,"<="&MIN(EOMONTH($AA29,0),$C$6))+($D$13="Oui")*SUMIFS(Donnees!$D$2:$D$2107,Donnees!$A$2:$A$2107,">="&MAX($AA29,$C$5),Donnees!$A$2:$A$2107,"<="&MIN(EOMONTH($AA29,0),$C$6))+($D$14="Oui")*SUMIFS(Donnees!$E$2:$E$2107,Donnees!$A$2:$A$2107,">="&MAX($AA29,$C$5),Donnees!$A$2:$A$2107,"<="&MIN(EOMONTH($AA29,0),$C$6))+($D$15="Oui")*SUMIFS(Donnees!$F$2:$F$2107,Donnees!$A$2:$A$2107,">="&MAX($AA29,$C$5),Donnees!$A$2:$A$2107,"<="&MIN(EOMONTH($AA29,0),$C$6))+($D$16="Oui")*SUMIFS(Donnees!$G$2:$G$2107,Donnees!$A$2:$A$2107,">="&MAX($AA29,$C$5),Donnees!$A$2:$A$2107,"<="&MIN(EOMONTH($AA29,0),$C$6))+($D$17="Oui")*SUMIFS(Donnees!$H$2:$H$2107,Donnees!$A$2:$A$2107,">="&MAX($AA29,$C$5),Donnees!$A$2:$A$2107,"<="&MIN(EOMONTH($AA29,0),$C$6))+($D$18="Oui")*SUMIFS(Donnees!$I$2:$I$2107,Donnees!$A$2:$A$2107,">="&MAX($AA29,$C$5),Donnees!$A$2:$A$2107,"<="&MIN(EOMONTH($AA29,0),$C$6)),NA()) -> #N/A
AA30: 42217 | AB30: =IF(AND(EOMONTH($AA30,0)>=$C$5,$AA30<=$C$6),($D$11="Oui")*SUMIFS(Donnees!$B$2:$B$2107,Donnees!$A$2:$A$2107,">="&MAX($AA30,$C$5),Donnees!$A$2:$A$2107,"<="&MIN(EOMONTH($AA30,0),$C$6))+($D$12="Oui")*SUMIFS(Donnees!$C$2:$C$2107,Donnees!$A$2:$A$2107,">="&MAX($AA30,$C$5),Donnees!$A$2:$A$2107,"<="&MIN(EOMONTH($AA30,0),$C$6))+($D$13="Oui")*SUMIFS(Donnees!$D$2:$D$2107,Donnees!$A$2:$A$2107,">="&MAX($AA30,$C$5),Donnees!$A$2:$A$2107,"<="&MIN(EOMONTH($AA30,0),$C$6))+($D$14="Oui")*SUMIFS(Donnees!$E$2:$E$2107,Donnees!$A$2:$A$2107,">="&MAX($AA30,$C$5),Donnees!$A$2:$A$2107,"<="&MIN(EOMONTH($AA30,0),$C$6))+($D$15="Oui")*SUMIFS(Donnees!$F$2:$F$2107,Donnees!$A$2:$A$2107,">="&MAX($AA30,$C$5),Donnees!$A$2:$A$2107,"<="&MIN(EOMONTH($AA30,0),$C$6))+($D$16="Oui")*SUMIFS(Donnees!$G$2:$G$2107,Donnees!$A$2:$A$2107,">="&MAX($AA30,$C$5),Donnees!$A$2:$A$2107,"<="&MIN(EOMONTH($AA30,0),$C$6))+($D$17="Oui")*SUMIFS(Donnees!$H$2:$H$2107,Donnees!$A$2:$A$2107,">="&MAX($AA30,$C$5),Donnees!$A$2:$A$2107,"<="&MIN(EOMONTH($AA30,0),$C$6))+($D$18="Oui")*SUMIFS(Donnees!$I$2:$I$2107,Donnees!$A$2:$A$2107,">="&MAX($AA30,$C$5),Donnees!$A$2:$A$2107,"<="&MIN(EOMONTH($AA30,0),$C$6)),NA()) -> #N/A
AA31: 42248 | AB31: =IF(AND(EOMONTH($AA31,0)>=$C$5,$AA31<=$C$6),($D$11="Oui")*SUMIFS(Donnees!$B$2:$B$2107,Donnees!$A$2:$A$2107,">="&MAX($AA31,$C$5),Donnees!$A$2:$A$2107,"<="&MIN(EOMONTH($AA31,0),$C$6))+($D$12="Oui")*SUMIFS(Donnees!$C$2:$C$2107,Donnees!$A$2:$A$2107,">="&MAX($AA31,$C$5),Donnees!$A$2:$A$2107,"<="&MIN(EOMONTH($AA31,0),$C$6))+($D$13="Oui")*SUMIFS(Donnees!$D$2:$D$2107,Donnees!$A$2:$A$2107,">="&MAX($AA31,$C$5),Donnees!$A$2:$A$2107,"<="&MIN(EOMONTH($AA31,0),$C$6))+($D$14="Oui")*SUMIFS(Donnees!$E$2:$E$2107,Donnees!$A$2:$A$2107,">="&MAX($AA31,$C$5),Donnees!$A$2:$A$2107,"<="&MIN(EOMONTH($AA31,0),$C$6))+($D$15="Oui")*SUMIFS(Donnees!$F$2:$F$2107,Donnees!$A$2:$A$2107,">="&MAX($AA31,$C$5),Donnees!$A$2:$A$2107,"<="&MIN(EOMONTH($AA31,0),$C$6))+($D$16="Oui")*SUMIFS(Donnees!$G$2:$G$2107,Donnees!$A$2:$A$2107,">="&MAX($AA31,$C$5),Donnees!$A$2:$A$2107,"<="&MIN(EOMONTH($AA31,0),$C$6))+($D$17="Oui")*SUMIFS(Donnees!$H$2:$H$2107,Donnees!$A$2:$A$2107,">="&MAX($AA31,$C$5),Donnees!$A$2:$A$2107,"<="&MIN(EOMONTH($AA31,0),$C$6))+($D$18="Oui")*SUMIFS(Donnees!$I$2:$I$2107,Donnees!$A$2:$A$2107,">="&MAX($AA31,$C$5),Donnees!$A$2:$A$2107,"<="&MIN(EOMONTH($AA31,0),$C$6)),NA()) -> #N/A
... AA38: 42461 | AB38: =IF(AND(EOMONTH($AA38,0)>=$C$5,$AA38<=$C$6),($D$11="Oui")*SUMIFS(Donnees!$B$2:$B$2107,Donnees!$A$2:$A$2107,">="&MAX($AA38,$C$5),Donnees!$A$2:$A$2107,"<="&MIN(EOMONTH($AA38,0),$C$6))+($D$12="Oui")*SUMIFS(Donnees!$C$2:$C$2107,Donnees!$A$2:$A$2107,">="&MAX($AA38,$C$5),Donnees!$A$2:$A$2107,"<="&MIN(EOMONTH($AA38,0),$C$6))+($D$13="Oui")*SUMIFS(Donnees!$D$2:$D$2107,Donnees!$A$2:$A$2107,">="&MAX($AA38,$C$5),Donnees!$A$2:$A$2107,"<="&MIN(EOMONTH($AA38,0),$C$6))+($D$14="Oui")*SUMIFS(Donnees!$E$2:$E$2107,Donnees!$A$2:$A$2107,">="&MAX($AA38,$C$5),Donnees!$A$2:$A$2107,"<="&MIN(EOMONTH($AA38,0),$C$6))+($D$15="Oui")*SUMIFS(Donnees!$F$2:$F$2107,Donnees!$A$2:$A$2107,">="&MAX($AA38,$C$5),Donnees!$A$2:$A$2107,"<="&MIN(EOMONTH($AA38,0),$C$6))+($D$16="Oui")*SUMIFS(Donnees!$G$2:$G$2107,Donnees!$A$2:$A$2107,">="&MAX($AA38,$C$5),Donnees!$A$2:$A$2107,"<="&MIN(EOMONTH($AA38,0),$C$6))+($D$17="Oui")*SUMIFS(Donnees!$H$2:$H$2107,Donnees!$A$2:$A$2107,">="&MAX($AA38,$C$5),Donnees!$A$2:$A$2107,"<="&MIN(EOMONTH($AA38,0),$C$6))+($D$18="Oui")*SUMIFS(Donnees!$I$2:$I$2107,Donnees!$A$2:$A$2107,">="&MAX($AA38,$C$5),Donnees!$A$2:$A$2107,"<="&MIN(EOMONTH($AA38,0),$C$6)),NA()) -> #N/A
B39: Détail jour par jour sur la période (tous les groupes) | AA39: 42491 | AB39: =IF(AND(EOMONTH($AA39,0)>=$C$5,$AA39<=$C$6),($D$11="Oui")*SUMIFS(Donnees!$B$2:$B$2107,Donnees!$A$2:$A$2107,">="&MAX($AA39,$C$5),Donnees!$A$2:$A$2107,"<="&MIN(EOMONTH($AA39,0),$C$6))+($D$12="Oui")*SUMIFS(Donnees!$C$2:$C$2107,Donnees!$A$2:$A$2107,">="&MAX($AA39,$C$5),Donnees!$A$2:$A$2107,"<="&MIN(EOMONTH($AA39,0),$C$6))+($D$13="Oui")*SUMIFS(Donnees!$D$2:$D$2107,Donnees!$A$2:$A$2107,">="&MAX($AA39,$C$5),Donnees!$A$2:$A$2107,"<="&MIN(EOMONTH($AA39,0),$C$6))+($D$14="Oui")*SUMIFS(Donnees!$E$2:$E$2107,Donnees!$A$2:$A$2107,">="&MAX($AA39,$C$5),Donnees!$A$2:$A$2107,"<="&MIN(EOMONTH($AA39,0),$C$6))+($D$15="Oui")*SUMIFS(Donnees!$F$2:$F$2107,Donnees!$A$2:$A$2107,">="&MAX($AA39,$C$5),Donnees!$A$2:$A$2107,"<="&MIN(EOMONTH($AA39,0),$C$6))+($D$16="Oui")*SUMIFS(Donnees!$G$2:$G$2107,Donnees!$A$2:$A$2107,">="&MAX($AA39,$C$5),Donnees!$A$2:$A$2107,"<="&MIN(EOMONTH($AA39,0),$C$6))+($D$17="Oui")*SUMIFS(Donnees!$H$2:$H$2107,Donnees!$A$2:$A$2107,">="&MAX($AA39,$C$5),Donnees!$A$2:$A$2107,"<="&MIN(EOMONTH($AA39,0),$C$6))+($D$18="Oui")*SUMIFS(Donnees!$I$2:$I$2107,Donnees!$A$2:$A$2107,">="&MAX($AA39,$C$5),Donnees!$A$2:$A$2107,"<="&MIN(EOMONTH($AA39,0),$C$6)),NA()) -> #N/A
B40: Date | C40: M01AB | D40: M01AE | E40: N02BA | F40: N02BE | G40: N05B | H40: N05C | I40: R03 | J40: R06 | AA40: 42522 | AB40: =IF(AND(EOMONTH($AA40,0)>=$C$5,$AA40<=$C$6),($D$11="Oui")*SUMIFS(Donnees!$B$2:$B$2107,Donnees!$A$2:$A$2107,">="&MAX($AA40,$C$5),Donnees!$A$2:$A$2107,"<="&MIN(EOMONTH($AA40,0),$C$6))+($D$12="Oui")*SUMIFS(Donnees!$C$2:$C$2107,Donnees!$A$2:$A$2107,">="&MAX($AA40,$C$5),Donnees!$A$2:$A$2107,"<="&MIN(EOMONTH($AA40,0),$C$6))+($D$13="Oui")*SUMIFS(Donnees!$D$2:$D$2107,Donnees!$A$2:$A$2107,">="&MAX($AA40,$C$5),Donnees!$A$2:$A$2107,"<="&MIN(EOMONTH($AA40,0),$C$6))+($D$14="Oui")*SUMIFS(Donnees!$E$2:$E$2107,Donnees!$A$2:$A$2107,">="&MAX($AA40,$C$5),Donnees!$A$2:$A$2107,"<="&MIN(EOMONTH($AA40,0),$C$6))+($D$15="Oui")*SUMIFS(Donnees!$F$2:$F$2107,Donnees!$A$2:$A$2107,">="&MAX($AA40,$C$5),Donnees!$A$2:$A$2107,"<="&MIN(EOMONTH($AA40,0),$C$6))+($D$16="Oui")*SUMIFS(Donnees!$G$2:$G$2107,Donnees!$A$2:$A$2107,">="&MAX($AA40,$C$5),Donnees!$A$2:$A$2107,"<="&MIN(EOMONTH($AA40,0),$C$6))+($D$17="Oui")*SUMIFS(Donnees!$H$2:$H$2107,Donnees!$A$2:$A$2107,">="&MAX($AA40,$C$5),Donnees!$A$2:$A$2107,"<="&MIN(EOMONTH($AA40,0),$C$6))+($D$18="Oui")*SUMIFS(Donnees!$I$2:$I$2107,Donnees!$A$2:$A$2107,">="&MAX($AA40,$C$5),Donnees!$A$2:$A$2107,"<="&MIN(EOMONTH($AA40,0),$C$6)),NA()) -> #N/A
B41: {=_xlfn._xlws.FILTER(Donnees!$A$2:$I$2107,(Donnees!$A$2:$A$2107>=$C$5)*(Donnees!$A$2:$A$2107<=$C$6),"Aucune donnée")} -> 43709 | C41: 2 | D41: 4.36 | E41: 5 | F41: 17 | G41: 8.2 | H41: 1 | I41: 5 | J41: 4 | AA41: 42552 | AB41: =IF(AND(EOMONTH($AA41,0)>=$C$5,$AA41<=$C$6),($D$11="Oui")*SUMIFS(Donnees!$B$2:$B$2107,Donnees!$A$2:$A$2107,">="&MAX($AA41,$C$5),Donnees!$A$2:$A$2107,"<="&MIN(EOMONTH($AA41,0),$C$6))+($D$12="Oui")*SUMIFS(Donnees!$C$2:$C$2107,Donnees!$A$2:$A$2107,">="&MAX($AA41,$C$5),Donnees!$A$2:$A$2107,"<="&MIN(EOMONTH($AA41,0),$C$6))+($D$13="Oui")*SUMIFS(Donnees!$D$2:$D$2107,Donnees!$A$2:$A$2107,">="&MAX($AA41,$C$5),Donnees!$A$2:$A$2107,"<="&MIN(EOMONTH($AA41,0),$C$6))+($D$14="Oui")*SUMIFS(Donnees!$E$2:$E$2107,Donnees!$A$2:$A$2107,">="&MAX($AA41,$C$5),Donnees!$A$2:$A$2107,"<="&MIN(EOMONTH($AA41,0),$C$6))+($D$15="Oui")*SUMIFS(Donnees!$F$2:$F$2107,Donnees!$A$2:$A$2107,">="&MAX($AA41,$C$5),Donnees!$A$2:$A$2107,"<="&MIN(EOMONTH($AA41,0),$C$6))+($D$16="Oui")*SUMIFS(Donnees!$G$2:$G$2107,Donnees!$A$2:$A$2107,">="&MAX($AA41,$C$5),Donnees!$A$2:$A$2107,"<="&MIN(EOMONTH($AA41,0),$C$6))+($D$17="Oui")*SUMIFS(Donnees!$H$2:$H$2107,Donnees!$A$2:$A$2107,">="&MAX($AA41,$C$5),Donnees!$A$2:$A$2107,"<="&MIN(EOMONTH($AA41,0),$C$6))+($D$18="Oui")*SUMIFS(Donnees!$I$2:$I$2107,Donnees!$A$2:$A$2107,">="&MAX($AA41,$C$5),Donnees!$A$2:$A$2107,"<="&MIN(EOMONTH($AA41,0),$C$6)),NA()) -> #N/A
B42: 43710 | C42: 5.33 | D42: 2.087 | E42: 2.5 | F42: 18 | G42: 7 | H42: 0 | I42: 1 | J42: 9 | AA42: 42583 | AB42: =IF(AND(EOMONTH($AA42,0)>=$C$5,$AA42<=$C$6),($D$11="Oui")*SUMIFS(Donnees!$B$2:$B$2107,Donnees!$A$2:$A$2107,">="&MAX($AA42,$C$5),Donnees!$A$2:$A$2107,"<="&MIN(EOMONTH($AA42,0),$C$6))+($D$12="Oui")*SUMIFS(Donnees!$C$2:$C$2107,Donnees!$A$2:$A$2107,">="&MAX($AA42,$C$5),Donnees!$A$2:$A$2107,"<="&MIN(EOMONTH($AA42,0),$C$6))+($D$13="Oui")*SUMIFS(Donnees!$D$2:$D$2107,Donnees!$A$2:$A$2107,">="&MAX($AA42,$C$5),Donnees!$A$2:$A$2107,"<="&MIN(EOMONTH($AA42,0),$C$6))+($D$14="Oui")*SUMIFS(Donnees!$E$2:$E$2107,Donnees!$A$2:$A$2107,">="&MAX($AA42,$C$5),Donnees!$A$2:$A$2107,"<="&MIN(EOMONTH($AA42,0),$C$6))+($D$15="Oui")*SUMIFS(Donnees!$F$2:$F$2107,Donnees!$A$2:$A$2107,">="&MAX($AA42,$C$5),Donnees!$A$2:$A$2107,"<="&MIN(EOMONTH($AA42,0),$C$6))+($D$16="Oui")*SUMIFS(Donnees!$G$2:$G$2107,Donnees!$A$2:$A$2107,">="&MAX($AA42,$C$5),Donnees!$A$2:$A$2107,"<="&MIN(EOMONTH($AA42,0),$C$6))+($D$17="Oui")*SUMIFS(Donnees!$H$2:$H$2107,Donnees!$A$2:$A$2107,">="&MAX($AA42,$C$5),Donnees!$A$2:$A$2107,"<="&MIN(EOMONTH($AA42,0),$C$6))+($D$18="Oui")*SUMIFS(Donnees!$I$2:$I$2107,Donnees!$A$2:$A$2107,">="&MAX($AA42,$C$5),Donnees!$A$2:$A$2107,"<="&MIN(EOMONTH($AA42,0),$C$6)),NA()) -> #N/A
B43: 43711 | C43: 9.36 | D43: 2.35 | E43: 3.1 | F43: 12.125 | G43: 8 | H43: 3 | I43: 1 | J43: 2 | AA43: 42614 | AB43: =IF(AND(EOMONTH($AA43,0)>=$C$5,$AA43<=$C$6),($D$11="Oui")*SUMIFS(Donnees!$B$2:$B$2107,Donnees!$A$2:$A$2107,">="&MAX($AA43,$C$5),Donnees!$A$2:$A$2107,"<="&MIN(EOMONTH($AA43,0),$C$6))+($D$12="Oui")*SUMIFS(Donnees!$C$2:$C$2107,Donnees!$A$2:$A$2107,">="&MAX($AA43,$C$5),Donnees!$A$2:$A$2107,"<="&MIN(EOMONTH($AA43,0),$C$6))+($D$13="Oui")*SUMIFS(Donnees!$D$2:$D$2107,Donnees!$A$2:$A$2107,">="&MAX($AA43,$C$5),Donnees!$A$2:$A$2107,"<="&MIN(EOMONTH($AA43,0),$C$6))+($D$14="Oui")*SUMIFS(Donnees!$E$2:$E$2107,Donnees!$A$2:$A$2107,">="&MAX($AA43,$C$5),Donnees!$A$2:$A$2107,"<="&MIN(EOMONTH($AA43,0),$C$6))+($D$15="Oui")*SUMIFS(Donnees!$F$2:$F$2107,Donnees!$A$2:$A$2107,">="&MAX($AA43,$C$5),Donnees!$A$2:$A$2107,"<="&MIN(EOMONTH($AA43,0),$C$6))+($D$16="Oui")*SUMIFS(Donnees!$G$2:$G$2107,Donnees!$A$2:$A$2107,">="&MAX($AA43,$C$5),Donnees!$A$2:$A$2107,"<="&MIN(EOMONTH($AA43,0),$C$6))+($D$17="Oui")*SUMIFS(Donnees!$H$2:$H$2107,Donnees!$A$2:$A$2107,">="&MAX($AA43,$C$5),Donnees!$A$2:$A$2107,"<="&MIN(EOMONTH($AA43,0),$C$6))+($D$18="Oui")*SUMIFS(Donnees!$I$2:$I$2107,Donnees!$A$2:$A$2107,">="&MAX($AA43,$C$5),Donnees!$A$2:$A$2107,"<="&MIN(EOMONTH($AA43,0),$C$6)),NA()) -> #N/A
B44: 43712 | C44: 2 | D44: 0.373 | E44: 2.15 | F44: 29.23 | G44: 7 | H44: 0 | I44: 3 | J44: 3 | AA44: 42644 | AB44: =IF(AND(EOMONTH($AA44,0)>=$C$5,$AA44<=$C$6),($D$11="Oui")*SUMIFS(Donnees!$B$2:$B$2107,Donnees!$A$2:$A$2107,">="&MAX($AA44,$C$5),Donnees!$A$2:$A$2107,"<="&MIN(EOMONTH($AA44,0),$C$6))+($D$12="Oui")*SUMIFS(Donnees!$C$2:$C$2107,Donnees!$A$2:$A$2107,">="&MAX($AA44,$C$5),Donnees!$A$2:$A$2107,"<="&MIN(EOMONTH($AA44,0),$C$6))+($D$13="Oui")*SUMIFS(Donnees!$D$2:$D$2107,Donnees!$A$2:$A$2107,">="&MAX($AA44,$C$5),Donnees!$A$2:$A$2107,"<="&MIN(EOMONTH($AA44,0),$C$6))+($D$14="Oui")*SUMIFS(Donnees!$E$2:$E$2107,Donnees!$A$2:$A$2107,">="&MAX($AA44,$C$5),Donnees!$A$2:$A$2107,"<="&MIN(EOMONTH($AA44,0),$C$6))+($D$15="Oui")*SUMIFS(Donnees!$F$2:$F$2107,Donnees!$A$2:$A$2107,">="&MAX($AA44,$C$5),Donnees!$A$2:$A$2107,"<="&MIN(EOMONTH($AA44,0),$C$6))+($D$16="Oui")*SUMIFS(Donnees!$G$2:$G$2107,Donnees!$A$2:$A$2107,">="&MAX($AA44,$C$5),Donnees!$A$2:$A$2107,"<="&MIN(EOMONTH($AA44,0),$C$6))+($D$17="Oui")*SUMIFS(Donnees!$H$2:$H$2107,Donnees!$A$2:$A$2107,">="&MAX($AA44,$C$5),Donnees!$A$2:$A$2107,"<="&MIN(EOMONTH($AA44,0),$C$6))+($D$18="Oui")*SUMIFS(Donnees!$I$2:$I$2107,Donnees!$A$2:$A$2107,">="&MAX($AA44,$C$5),Donnees!$A$2:$A$2107,"<="&MIN(EOMONTH($AA44,0),$C$6)),NA()) -> #N/A
B45: 43713 | C45: 7 | D45: 9.53 | E45: 2 | F45: 14 | G45: 1 | H45: 0 | I45: 1 | J45: 8 | AA45: 42675 | AB45: =IF(AND(EOMONTH($AA45,0)>=$C$5,$AA45<=$C$6),($D$11="Oui")*SUMIFS(Donnees!$B$2:$B$2107,Donnees!$A$2:$A$2107,">="&MAX($AA45,$C$5),Donnees!$A$2:$A$2107,"<="&MIN(EOMONTH($AA45,0),$C$6))+($D$12="Oui")*SUMIFS(Donnees!$C$2:$C$2107,Donnees!$A$2:$A$2107,">="&MAX($AA45,$C$5),Donnees!$A$2:$A$2107,"<="&MIN(EOMONTH($AA45,0),$C$6))+($D$13="Oui")*SUMIFS(Donnees!$D$2:$D$2107,Donnees!$A$2:$A$2107,">="&MAX($AA45,$C$5),Donnees!$A$2:$A$2107,"<="&MIN(EOMONTH($AA45,0),$C$6))+($D$14="Oui")*SUMIFS(Donnees!$E$2:$E$2107,Donnees!$A$2:$A$2107,">="&MAX($AA45,$C$5),Donnees!$A$2:$A$2107,"<="&MIN(EOMONTH($AA45,0),$C$6))+($D$15="Oui")*SUMIFS(Donnees!$F$2:$F$2107,Donnees!$A$2:$A$2107,">="&MAX($AA45,$C$5),Donnees!$A$2:$A$2107,"<="&MIN(EOMONTH($AA45,0),$C$6))+($D$16="Oui")*SUMIFS(Donnees!$G$2:$G$2107,Donnees!$A$2:$A$2107,">="&MAX($AA45,$C$5),Donnees!$A$2:$A$2107,"<="&MIN(EOMONTH($AA45,0),$C$6))+($D$17="Oui")*SUMIFS(Donnees!$H$2:$H$2107,Donnees!$A$2:$A$2107,">="&MAX($AA45,$C$5),Donnees!$A$2:$A$2107,"<="&MIN(EOMONTH($AA45,0),$C$6))+($D$18="Oui")*SUMIFS(Donnees!$I$2:$I$2107,Donnees!$A$2:$A$2107,">="&MAX($AA45,$C$5),Donnees!$A$2:$A$2107,"<="&MIN(EOMONTH($AA45,0),$C$6)),NA()) -> #N/A
B46: 43714 | C46: 1.68 | D46: 2.67 | E46: 1 | F46: 28.4 | G46: 7 | H46: 0 | I46: 0 | J46: 1.5 | AA46: 42705 | AB46: =IF(AND(EOMONTH($AA46,0)>=$C$5,$AA46<=$C$6),($D$11="Oui")*SUMIFS(Donnees!$B$2:$B$2107,Donnees!$A$2:$A$2107,">="&MAX($AA46,$C$5),Donnees!$A$2:$A$2107,"<="&MIN(EOMONTH($AA46,0),$C$6))+($D$12="Oui")*SUMIFS(Donnees!$C$2:$C$2107,Donnees!$A$2:$A$2107,">="&MAX($AA46,$C$5),Donnees!$A$2:$A$2107,"<="&MIN(EOMONTH($AA46,0),$C$6))+($D$13="Oui")*SUMIFS(Donnees!$D$2:$D$2107,Donnees!$A$2:$A$2107,">="&MAX($AA46,$C$5),Donnees!$A$2:$A$2107,"<="&MIN(EOMONTH($AA46,0),$C$6))+($D$14="Oui")*SUMIFS(Donnees!$E$2:$E$2107,Donnees!$A$2:$A$2107,">="&MAX($AA46,$C$5),Donnees!$A$2:$A$2107,"<="&MIN(EOMONTH($AA46,0),$C$6))+($D$15="Oui")*SUMIFS(Donnees!$F$2:$F$2107,Donnees!$A$2:$A$2107,">="&MAX($AA46,$C$5),Donnees!$A$2:$A$2107,"<="&MIN(EOMONTH($AA46,0),$C$6))+($D$16="Oui")*SUMIFS(Donnees!$G$2:$G$2107,Donnees!$A$2:$A$2107,">="&MAX($AA46,$C$5),Donnees!$A$2:$A$2107,"<="&MIN(EOMONTH($AA46,0),$C$6))+($D$17="Oui")*SUMIFS(Donnees!$H$2:$H$2107,Donnees!$A$2:$A$2107,">="&MAX($AA46,$C$5),Donnees!$A$2:$A$2107,"<="&MIN(EOMONTH($AA46,0),$C$6))+($D$18="Oui")*SUMIFS(Donnees!$I$2:$I$2107,Donnees!$A$2:$A$2107,">="&MAX($AA46,$C$5),Donnees!$A$2:$A$2107,"<="&MIN(EOMONTH($AA46,0),$C$6)),NA()) -> #N/A
B47: 43715 | C47: 8.33 | D47: 3.67 | E47: 2 | F47: 27 | G47: 14 | H47: 3 | I47: 6 | J47: 2 | AA47: 42736 | AB47: =IF(AND(EOMONTH($AA47,0)>=$C$5,$AA47<=$C$6),($D$11="Oui")*SUMIFS(Donnees!$B$2:$B$2107,Donnees!$A$2:$A$2107,">="&MAX($AA47,$C$5),Donnees!$A$2:$A$2107,"<="&MIN(EOMONTH($AA47,0),$C$6))+($D$12="Oui")*SUMIFS(Donnees!$C$2:$C$2107,Donnees!$A$2:$A$2107,">="&MAX($AA47,$C$5),Donnees!$A$2:$A$2107,"<="&MIN(EOMONTH($AA47,0),$C$6))+($D$13="Oui")*SUMIFS(Donnees!$D$2:$D$2107,Donnees!$A$2:$A$2107,">="&MAX($AA47,$C$5),Donnees!$A$2:$A$2107,"<="&MIN(EOMONTH($AA47,0),$C$6))+($D$14="Oui")*SUMIFS(Donnees!$E$2:$E$2107,Donnees!$A$2:$A$2107,">="&MAX($AA47,$C$5),Donnees!$A$2:$A$2107,"<="&MIN(EOMONTH($AA47,0),$C$6))+($D$15="Oui")*SUMIFS(Donnees!$F$2:$F$2107,Donnees!$A$2:$A$2107,">="&MAX($AA47,$C$5),Donnees!$A$2:$A$2107,"<="&MIN(EOMONTH($AA47,0),$C$6))+($D$16="Oui")*SUMIFS(Donnees!$G$2:$G$2107,Donnees!$A$2:$A$2107,">="&MAX($AA47,$C$5),Donnees!$A$2:$A$2107,"<="&MIN(EOMONTH($AA47,0),$C$6))+($D$17="Oui")*SUMIFS(Donnees!$H$2:$H$2107,Donnees!$A$2:$A$2107,">="&MAX($AA47,$C$5),Donnees!$A$2:$A$2107,"<="&MIN(EOMONTH($AA47,0),$C$6))+($D$18="Oui")*SUMIFS(Donnees!$I$2:$I$2107,Donnees!$A$2:$A$2107,">="&MAX($AA47,$C$5),Donnees!$A$2:$A$2107,"<="&MIN(EOMONTH($AA47,0),$C$6)),NA()) -> #N/A
B48: 43716 | C48: 7.01 | D48: 6.087 | E48: 3 | F48: 26 | G48: 7 | H48: 0 | I48: 3 | J48: 3 | AA48: 42767 | AB48: =IF(AND(EOMONTH($AA48,0)>=$C$5,$AA48<=$C$6),($D$11="Oui")*SUMIFS(Donnees!$B$2:$B$2107,Donnees!$A$2:$A$2107,">="&MAX($AA48,$C$5),Donnees!$A$2:$A$2107,"<="&MIN(EOMONTH($AA48,0),$C$6))+($D$12="Oui")*SUMIFS(Donnees!$C$2:$C$2107,Donnees!$A$2:$A$2107,">="&MAX($AA48,$C$5),Donnees!$A$2:$A$2107,"<="&MIN(EOMONTH($AA48,0),$C$6))+($D$13="Oui")*SUMIFS(Donnees!$D$2:$D$2107,Donnees!$A$2:$A$2107,">="&MAX($AA48,$C$5),Donnees!$A$2:$A$2107,"<="&MIN(EOMONTH($AA48,0),$C$6))+($D$14="Oui")*SUMIFS(Donnees!$E$2:$E$2107,Donnees!$A$2:$A$2107,">="&MAX($AA48,$C$5),Donnees!$A$2:$A$2107,"<="&MIN(EOMONTH($AA48,0),$C$6))+($D$15="Oui")*SUMIFS(Donnees!$F$2:$F$2107,Donnees!$A$2:$A$2107,">="&MAX($AA48,$C$5),Donnees!$A$2:$A$2107,"<="&MIN(EOMONTH($AA48,0),$C$6))+($D$16="Oui")*SUMIFS(Donnees!$G$2:$G$2107,Donnees!$A$2:$A$2107,">="&MAX($AA48,$C$5),Donnees!$A$2:$A$2107,"<="&MIN(EOMONTH($AA48,0),$C$6))+($D$17="Oui")*SUMIFS(Donnees!$H$2:$H$2107,Donnees!$A$2:$A$2107,">="&MAX($AA48,$C$5),Donnees!$A$2:$A$2107,"<="&MIN(EOMONTH($AA48,0),$C$6))+($D$18="Oui")*SUMIFS(Donnees!$I$2:$I$2107,Donnees!$A$2:$A$2107,">="&MAX($AA48,$C$5),Donnees!$A$2:$A$2107,"<="&MIN(EOMONTH($AA48,0),$C$6)),NA()) -> #N/A
B49: 43717 | C49: 1.18 | D49: 2.124 | E49: 3 | F49: 26 | G49: 4 | H49: 3 | I49: 5 | J49: 2 | AA49: 42795 | AB49: =IF(AND(EOMONTH($AA49,0)>=$C$5,$AA49<=$C$6),($D$11="Oui")*SUMIFS(Donnees!$B$2:$B$2107,Donnees!$A$2:$A$2107,">="&MAX($AA49,$C$5),Donnees!$A$2:$A$2107,"<="&MIN(EOMONTH($AA49,0),$C$6))+($D$12="Oui")*SUMIFS(Donnees!$C$2:$C$2107,Donnees!$A$2:$A$2107,">="&MAX($AA49,$C$5),Donnees!$A$2:$A$2107,"<="&MIN(EOMONTH($AA49,0),$C$6))+($D$13="Oui")*SUMIFS(Donnees!$D$2:$D$2107,Donnees!$A$2:$A$2107,">="&MAX($AA49,$C$5),Donnees!$A$2:$A$2107,"<="&MIN(EOMONTH($AA49,0),$C$6))+($D$14="Oui")*SUMIFS(Donnees!$E$2:$E$2107,Donnees!$A$2:$A$2107,">="&MAX($AA49,$C$5),Donnees!$A$2:$A$2107,"<="&MIN(EOMONTH($AA49,0),$C$6))+($D$15="Oui")*SUMIFS(Donnees!$F$2:$F$2107,Donnees!$A$2:$A$2107,">="&MAX($AA49,$C$5),Donnees!$A$2:$A$2107,"<="&MIN(EOMONTH($AA49,0),$C$6))+($D$16="Oui")*SUMIFS(Donnees!$G$2:$G$2107,Donnees!$A$2:$A$2107,">="&MAX($AA49,$C$5),Donnees!$A$2:$A$2107,"<="&MIN(EOMONTH($AA49,0),$C$6))+($D$17="Oui")*SUMIFS(Donnees!$H$2:$H$2107,Donnees!$A$2:$A$2107,">="&MAX($AA49,$C$5),Donnees!$A$2:$A$2107,"<="&MIN(EOMONTH($AA49,0),$C$6))+($D$18="Oui")*SUMIFS(Donnees!$I$2:$I$2107,Donnees!$A$2:$A$2107,">="&MAX($AA49,$C$5),Donnees!$A$2:$A$2107,"<="&MIN(EOMONTH($AA49,0),$C$6)),NA()) -> #N/A
B50: 43718 | C50: 8.66 | D50: 6.68 | E50: 4.2 | F50: 22 | G50: 17 | H50: 0 | I50: 1 | J50: 1 | AA50: 42826 | AB50: =IF(AND(EOMONTH($AA50,0)>=$C$5,$AA50<=$C$6),($D$11="Oui")*SUMIFS(Donnees!$B$2:$B$2107,Donnees!$A$2:$A$2107,">="&MAX($AA50,$C$5),Donnees!$A$2:$A$2107,"<="&MIN(EOMONTH($AA50,0),$C$6))+($D$12="Oui")*SUMIFS(Donnees!$C$2:$C$2107,Donnees!$A$2:$A$2107,">="&MAX($AA50,$C$5),Donnees!$A$2:$A$2107,"<="&MIN(EOMONTH($AA50,0),$C$6))+($D$13="Oui")*SUMIFS(Donnees!$D$2:$D$2107,Donnees!$A$2:$A$2107,">="&MAX($AA50,$C$5),Donnees!$A$2:$A$2107,"<="&MIN(EOMONTH($AA50,0),$C$6))+($D$14="Oui")*SUMIFS(Donnees!$E$2:$E$2107,Donnees!$A$2:$A$2107,">="&MAX($AA50,$C$5),Donnees!$A$2:$A$2107,"<="&MIN(EOMONTH($AA50,0),$C$6))+($D$15="Oui")*SUMIFS(Donnees!$F$2:$F$2107,Donnees!$A$2:$A$2107,">="&MAX($AA50,$C$5),Donnees!$A$2:$A$2107,"<="&MIN(EOMONTH($AA50,0),$C$6))+($D$16="Oui")*SUMIFS(Donnees!$G$2:$G$2107,Donnees!$A$2:$A$2107,">="&MAX($AA50,$C$5),Donnees!$A$2:$A$2107,"<="&MIN(EOMONTH($AA50,0),$C$6))+($D$17="Oui")*SUMIFS(Donnees!$H$2:$H$2107,Donnees!$A$2:$A$2107,">="&MAX($AA50,$C$5),Donnees!$A$2:$A$2107,"<="&MIN(EOMONTH($AA50,0),$C$6))+($D$18="Oui")*SUMIFS(Donnees!$I$2:$I$2107,Donnees!$A$2:$A$2107,">="&MAX($AA50,$C$5),Donnees!$A$2:$A$2107,"<="&MIN(EOMONTH($AA50,0),$C$6)),NA()) -> #N/A
B51: 43719 | C51: 2.67 | D51: 5.076 | E51: 3 | F51: 42 | G51: 5 | H51: 0 | I51: 5 | J51: 2.5 | AA51: 42856 | AB51: =IF(AND(EOMONTH($AA51,0)>=$C$5,$AA51<=$C$6),($D$11="Oui")*SUMIFS(Donnees!$B$2:$B$2107,Donnees!$A$2:$A$2107,">="&MAX($AA51,$C$5),Donnees!$A$2:$A$2107,"<="&MIN(EOMONTH($AA51,0),$C$6))+($D$12="Oui")*SUMIFS(Donnees!$C$2:$C$2107,Donnees!$A$2:$A$2107,">="&MAX($AA51,$C$5),Donnees!$A$2:$A$2107,"<="&MIN(EOMONTH($AA51,0),$C$6))+($D$13="Oui")*SUMIFS(Donnees!$D$2:$D$2107,Donnees!$A$2:$A$2107,">="&MAX($AA51,$C$5),Donnees!$A$2:$A$2107,"<="&MIN(EOMONTH($AA51,0),$C$6))+($D$14="Oui")*SUMIFS(Donnees!$E$2:$E$2107,Donnees!$A$2:$A$2107,">="&MAX($AA51,$C$5),Donnees!$A$2:$A$2107,"<="&MIN(EOMONTH($AA51,0),$C$6))+($D$15="Oui")*SUMIFS(Donnees!$F$2:$F$2107,Donnees!$A$2:$A$2107,">="&MAX($AA51,$C$5),Donnees!$A$2:$A$2107,"<="&MIN(EOMONTH($AA51,0),$C$6))+($D$16="Oui")*SUMIFS(Donnees!$G$2:$G$2107,Donnees!$A$2:$A$2107,">="&MAX($AA51,$C$5),Donnees!$A$2:$A$2107,"<="&MIN(EOMONTH($AA51,0),$C$6))+($D$17="Oui")*SUMIFS(Donnees!$H$2:$H$2107,Donnees!$A$2:$A$2107,">="&MAX($AA51,$C$5),Donnees!$A$2:$A$2107,"<="&MIN(EOMONTH($AA51,0),$C$6))+($D$18="Oui")*SUMIFS(Donnees!$I$2:$I$2107,Donnees!$A$2:$A$2107,">="&MAX($AA51,$C$5),Donnees!$A$2:$A$2107,"<="&MIN(EOMONTH($AA51,0),$C$6)),NA()) -> #N/A
B52: 43720 | C52: 2.33 | D52: 1.34 | E52: 2 | F52: 21.975 | G52: 11.2 | H52: 0 | I52: 10 | J52: 4 | AA52: 42887 | AB52: =IF(AND(EOMONTH($AA52,0)>=$C$5,$AA52<=$C$6),($D$11="Oui")*SUMIFS(Donnees!$B$2:$B$2107,Donnees!$A$2:$A$2107,">="&MAX($AA52,$C$5),Donnees!$A$2:$A$2107,"<="&MIN(EOMONTH($AA52,0),$C$6))+($D$12="Oui")*SUMIFS(Donnees!$C$2:$C$2107,Donnees!$A$2:$A$2107,">="&MAX($AA52,$C$5),Donnees!$A$2:$A$2107,"<="&MIN(EOMONTH($AA52,0),$C$6))+($D$13="Oui")*SUMIFS(Donnees!$D$2:$D$2107,Donnees!$A$2:$A$2107,">="&MAX($AA52,$C$5),Donnees!$A$2:$A$2107,"<="&MIN(EOMONTH($AA52,0),$C$6))+($D$14="Oui")*SUMIFS(Donnees!$E$2:$E$2107,Donnees!$A$2:$A$2107,">="&MAX($AA52,$C$5),Donnees!$A$2:$A$2107,"<="&MIN(EOMONTH($AA52,0),$C$6))+($D$15="Oui")*SUMIFS(Donnees!$F$2:$F$2107,Donnees!$A$2:$A$2107,">="&MAX($AA52,$C$5),Donnees!$A$2:$A$2107,"<="&MIN(EOMONTH($AA52,0),$C$6))+($D$16="Oui")*SUMIFS(Donnees!$G$2:$G$2107,Donnees!$A$2:$A$2107,">="&MAX($AA52,$C$5),Donnees!$A$2:$A$2107,"<="&MIN(EOMONTH($AA52,0),$C$6))+($D$17="Oui")*SUMIFS(Donnees!$H$2:$H$2107,Donnees!$A$2:$A$2107,">="&MAX($AA52,$C$5),Donnees!$A$2:$A$2107,"<="&MIN(EOMONTH($AA52,0),$C$6))+($D$18="Oui")*SUMIFS(Donnees!$I$2:$I$2107,Donnees!$A$2:$A$2107,">="&MAX($AA52,$C$5),Donnees!$A$2:$A$2107,"<="&MIN(EOMONTH($AA52,0),$C$6)),NA()) -> #N/A
B53: 43721 | C53: 6.34 | D53: 3.35 | E53: 2 | F53: 17 | G53: 12 | H53: 2 | I53: 5 | J53: 5 | AA53: 42917 | AB53: =IF(AND(EOMONTH($AA53,0)>=$C$5,$AA53<=$C$6),($D$11="Oui")*SUMIFS(Donnees!$B$2:$B$2107,Donnees!$A$2:$A$2107,">="&MAX($AA53,$C$5),Donnees!$A$2:$A$2107,"<="&MIN(EOMONTH($AA53,0),$C$6))+($D$12="Oui")*SUMIFS(Donnees!$C$2:$C$2107,Donnees!$A$2:$A$2107,">="&MAX($AA53,$C$5),Donnees!$A$2:$A$2107,"<="&MIN(EOMONTH($AA53,0),$C$6))+($D$13="Oui")*SUMIFS(Donnees!$D$2:$D$2107,Donnees!$A$2:$A$2107,">="&MAX($AA53,$C$5),Donnees!$A$2:$A$2107,"<="&MIN(EOMONTH($AA53,0),$C$6))+($D$14="Oui")*SUMIFS(Donnees!$E$2:$E$2107,Donnees!$A$2:$A$2107,">="&MAX($AA53,$C$5),Donnees!$A$2:$A$2107,"<="&MIN(EOMONTH($AA53,0),$C$6))+($D$15="Oui")*SUMIFS(Donnees!$F$2:$F$2107,Donnees!$A$2:$A$2107,">="&MAX($AA53,$C$5),Donnees!$A$2:$A$2107,"<="&MIN(EOMONTH($AA53,0),$C$6))+($D$16="Oui")*SUMIFS(Donnees!$G$2:$G$2107,Donnees!$A$2:$A$2107,">="&MAX($AA53,$C$5),Donnees!$A$2:$A$2107,"<="&MIN(EOMONTH($AA53,0),$C$6))+($D$17="Oui")*SUMIFS(Donnees!$H$2:$H$2107,Donnees!$A$2:$A$2107,">="&MAX($AA53,$C$5),Donnees!$A$2:$A$2107,"<="&MIN(EOMONTH($AA53,0),$C$6))+($D$18="Oui")*SUMIFS(Donnees!$I$2:$I$2107,Donnees!$A$2:$A$2107,">="&MAX($AA53,$C$5),Donnees!$A$2:$A$2107,"<="&MIN(EOMONTH($AA53,0),$C$6)),NA()) -> #N/A
... B70: 43738 | C70: 2 | D70: 1.439 | E70: 2.1 | F70: 49.4 | G70: 9 | H70: 0 | I70: 5 | J70: 2 | AA70: 43435 | AB70: =IF(AND(EOMONTH($AA70,0)>=$C$5,$AA70<=$C$6),($D$11="Oui")*SUMIFS(Donnees!$B$2:$B$2107,Donnees!$A$2:$A$2107,">="&MAX($AA70,$C$5),Donnees!$A$2:$A$2107,"<="&MIN(EOMONTH($AA70,0),$C$6))+($D$12="Oui")*SUMIFS(Donnees!$C$2:$C$2107,Donnees!$A$2:$A$2107,">="&MAX($AA70,$C$5),Donnees!$A$2:$A$2107,"<="&MIN(EOMONTH($AA70,0),$C$6))+($D$13="Oui")*SUMIFS(Donnees!$D$2:$D$2107,Donnees!$A$2:$A$2107,">="&MAX($AA70,$C$5),Donnees!$A$2:$A$2107,"<="&MIN(EOMONTH($AA70,0),$C$6))+($D$14="Oui")*SUMIFS(Donnees!$E$2:$E$2107,Donnees!$A$2:$A$2107,">="&MAX($AA70,$C$5),Donnees!$A$2:$A$2107,"<="&MIN(EOMONTH($AA70,0),$C$6))+($D$15="Oui")*SUMIFS(Donnees!$F$2:$F$2107,Donnees!$A$2:$A$2107,">="&MAX($AA70,$C$5),Donnees!$A$2:$A$2107,"<="&MIN(EOMONTH($AA70,0),$C$6))+($D$16="Oui")*SUMIFS(Donnees!$G$2:$G$2107,Donnees!$A$2:$A$2107,">="&MAX($AA70,$C$5),Donnees!$A$2:$A$2107,"<="&MIN(EOMONTH($AA70,0),$C$6))+($D$17="Oui")*SUMIFS(Donnees!$H$2:$H$2107,Donnees!$A$2:$A$2107,">="&MAX($AA70,$C$5),Donnees!$A$2:$A$2107,"<="&MIN(EOMONTH($AA70,0),$C$6))+($D$18="Oui")*SUMIFS(Donnees!$I$2:$I$2107,Donnees!$A$2:$A$2107,">="&MAX($AA70,$C$5),Donnees!$A$2:$A$2107,"<="&MIN(EOMONTH($AA70,0),$C$6)),NA()) -> #N/A
AA71: 43466 | AB71: =IF(AND(EOMONTH($AA71,0)>=$C$5,$AA71<=$C$6),($D$11="Oui")*SUMIFS(Donnees!$B$2:$B$2107,Donnees!$A$2:$A$2107,">="&MAX($AA71,$C$5),Donnees!$A$2:$A$2107,"<="&MIN(EOMONTH($AA71,0),$C$6))+($D$12="Oui")*SUMIFS(Donnees!$C$2:$C$2107,Donnees!$A$2:$A$2107,">="&MAX($AA71,$C$5),Donnees!$A$2:$A$2107,"<="&MIN(EOMONTH($AA71,0),$C$6))+($D$13="Oui")*SUMIFS(Donnees!$D$2:$D$2107,Donnees!$A$2:$A$2107,">="&MAX($AA71,$C$5),Donnees!$A$2:$A$2107,"<="&MIN(EOMONTH($AA71,0),$C$6))+($D$14="Oui")*SUMIFS(Donnees!$E$2:$E$2107,Donnees!$A$2:$A$2107,">="&MAX($AA71,$C$5),Donnees!$A$2:$A$2107,"<="&MIN(EOMONTH($AA71,0),$C$6))+($D$15="Oui")*SUMIFS(Donnees!$F$2:$F$2107,Donnees!$A$2:$A$2107,">="&MAX($AA71,$C$5),Donnees!$A$2:$A$2107,"<="&MIN(EOMONTH($AA71,0),$C$6))+($D$16="Oui")*SUMIFS(Donnees!$G$2:$G$2107,Donnees!$A$2:$A$2107,">="&MAX($AA71,$C$5),Donnees!$A$2:$A$2107,"<="&MIN(EOMONTH($AA71,0),$C$6))+($D$17="Oui")*SUMIFS(Donnees!$H$2:$H$2107,Donnees!$A$2:$A$2107,">="&MAX($AA71,$C$5),Donnees!$A$2:$A$2107,"<="&MIN(EOMONTH($AA71,0),$C$6))+($D$18="Oui")*SUMIFS(Donnees!$I$2:$I$2107,Donnees!$A$2:$A$2107,">="&MAX($AA71,$C$5),Donnees!$A$2:$A$2107,"<="&MIN(EOMONTH($AA71,0),$C$6)),NA()) -> #N/A
AA72: 43497 | AB72: =IF(AND(EOMONTH($AA72,0)>=$C$5,$AA72<=$C$6),($D$11="Oui")*SUMIFS(Donnees!$B$2:$B$2107,Donnees!$A$2:$A$2107,">="&MAX($AA72,$C$5),Donnees!$A$2:$A$2107,"<="&MIN(EOMONTH($AA72,0),$C$6))+($D$12="Oui")*SUMIFS(Donnees!$C$2:$C$2107,Donnees!$A$2:$A$2107,">="&MAX($AA72,$C$5),Donnees!$A$2:$A$2107,"<="&MIN(EOMONTH($AA72,0),$C$6))+($D$13="Oui")*SUMIFS(Donnees!$D$2:$D$2107,Donnees!$A$2:$A$2107,">="&MAX($AA72,$C$5),Donnees!$A$2:$A$2107,"<="&MIN(EOMONTH($AA72,0),$C$6))+($D$14="Oui")*SUMIFS(Donnees!$E$2:$E$2107,Donnees!$A$2:$A$2107,">="&MAX($AA72,$C$5),Donnees!$A$2:$A$2107,"<="&MIN(EOMONTH($AA72,0),$C$6))+($D$15="Oui")*SUMIFS(Donnees!$F$2:$F$2107,Donnees!$A$2:$A$2107,">="&MAX($AA72,$C$5),Donnees!$A$2:$A$2107,"<="&MIN(EOMONTH($AA72,0),$C$6))+($D$16="Oui")*SUMIFS(Donnees!$G$2:$G$2107,Donnees!$A$2:$A$2107,">="&MAX($AA72,$C$5),Donnees!$A$2:$A$2107,"<="&MIN(EOMONTH($AA72,0),$C$6))+($D$17="Oui")*SUMIFS(Donnees!$H$2:$H$2107,Donnees!$A$2:$A$2107,">="&MAX($AA72,$C$5),Donnees!$A$2:$A$2107,"<="&MIN(EOMONTH($AA72,0),$C$6))+($D$18="Oui")*SUMIFS(Donnees!$I$2:$I$2107,Donnees!$A$2:$A$2107,">="&MAX($AA72,$C$5),Donnees!$A$2:$A$2107,"<="&MIN(EOMONTH($AA72,0),$C$6)),NA()) -> #N/A
AA73: 43525 | AB73: =IF(AND(EOMONTH($AA73,0)>=$C$5,$AA73<=$C$6),($D$11="Oui")*SUMIFS(Donnees!$B$2:$B$2107,Donnees!$A$2:$A$2107,">="&MAX($AA73,$C$5),Donnees!$A$2:$A$2107,"<="&MIN(EOMONTH($AA73,0),$C$6))+($D$12="Oui")*SUMIFS(Donnees!$C$2:$C$2107,Donnees!$A$2:$A$2107,">="&MAX($AA73,$C$5),Donnees!$A$2:$A$2107,"<="&MIN(EOMONTH($AA73,0),$C$6))+($D$13="Oui")*SUMIFS(Donnees!$D$2:$D$2107,Donnees!$A$2:$A$2107,">="&MAX($AA73,$C$5),Donnees!$A$2:$A$2107,"<="&MIN(EOMONTH($AA73,0),$C$6))+($D$14="Oui")*SUMIFS(Donnees!$E$2:$E$2107,Donnees!$A$2:$A$2107,">="&MAX($AA73,$C$5),Donnees!$A$2:$A$2107,"<="&MIN(EOMONTH($AA73,0),$C$6))+($D$15="Oui")*SUMIFS(Donnees!$F$2:$F$2107,Donnees!$A$2:$A$2107,">="&MAX($AA73,$C$5),Donnees!$A$2:$A$2107,"<="&MIN(EOMONTH($AA73,0),$C$6))+($D$16="Oui")*SUMIFS(Donnees!$G$2:$G$2107,Donnees!$A$2:$A$2107,">="&MAX($AA73,$C$5),Donnees!$A$2:$A$2107,"<="&MIN(EOMONTH($AA73,0),$C$6))+($D$17="Oui")*SUMIFS(Donnees!$H$2:$H$2107,Donnees!$A$2:$A$2107,">="&MAX($AA73,$C$5),Donnees!$A$2:$A$2107,"<="&MIN(EOMONTH($AA73,0),$C$6))+($D$18="Oui")*SUMIFS(Donnees!$I$2:$I$2107,Donnees!$A$2:$A$2107,">="&MAX($AA73,$C$5),Donnees!$A$2:$A$2107,"<="&MIN(EOMONTH($AA73,0),$C$6)),NA()) -> #N/A
AA74: 43556 | AB74: =IF(AND(EOMONTH($AA74,0)>=$C$5,$AA74<=$C$6),($D$11="Oui")*SUMIFS(Donnees!$B$2:$B$2107,Donnees!$A$2:$A$2107,">="&MAX($AA74,$C$5),Donnees!$A$2:$A$2107,"<="&MIN(EOMONTH($AA74,0),$C$6))+($D$12="Oui")*SUMIFS(Donnees!$C$2:$C$2107,Donnees!$A$2:$A$2107,">="&MAX($AA74,$C$5),Donnees!$A$2:$A$2107,"<="&MIN(EOMONTH($AA74,0),$C$6))+($D$13="Oui")*SUMIFS(Donnees!$D$2:$D$2107,Donnees!$A$2:$A$2107,">="&MAX($AA74,$C$5),Donnees!$A$2:$A$2107,"<="&MIN(EOMONTH($AA74,0),$C$6))+($D$14="Oui")*SUMIFS(Donnees!$E$2:$E$2107,Donnees!$A$2:$A$2107,">="&MAX($AA74,$C$5),Donnees!$A$2:$A$2107,"<="&MIN(EOMONTH($AA74,0),$C$6))+($D$15="Oui")*SUMIFS(Donnees!$F$2:$F$2107,Donnees!$A$2:$A$2107,">="&MAX($AA74,$C$5),Donnees!$A$2:$A$2107,"<="&MIN(EOMONTH($AA74,0),$C$6))+($D$16="Oui")*SUMIFS(Donnees!$G$2:$G$2107,Donnees!$A$2:$A$2107,">="&MAX($AA74,$C$5),Donnees!$A$2:$A$2107,"<="&MIN(EOMONTH($AA74,0),$C$6))+($D$17="Oui")*SUMIFS(Donnees!$H$2:$H$2107,Donnees!$A$2:$A$2107,">="&MAX($AA74,$C$5),Donnees!$A$2:$A$2107,"<="&MIN(EOMONTH($AA74,0),$C$6))+($D$18="Oui")*SUMIFS(Donnees!$I$2:$I$2107,Donnees!$A$2:$A$2107,">="&MAX($AA74,$C$5),Donnees!$A$2:$A$2107,"<="&MIN(EOMONTH($AA74,0),$C$6)),NA()) -> #N/A
AA75: 43586 | AB75: =IF(AND(EOMONTH($AA75,0)>=$C$5,$AA75<=$C$6),($D$11="Oui")*SUMIFS(Donnees!$B$2:$B$2107,Donnees!$A$2:$A$2107,">="&MAX($AA75,$C$5),Donnees!$A$2:$A$2107,"<="&MIN(EOMONTH($AA75,0),$C$6))+($D$12="Oui")*SUMIFS(Donnees!$C$2:$C$2107,Donnees!$A$2:$A$2107,">="&MAX($AA75,$C$5),Donnees!$A$2:$A$2107,"<="&MIN(EOMONTH($AA75,0),$C$6))+($D$13="Oui")*SUMIFS(Donnees!$D$2:$D$2107,Donnees!$A$2:$A$2107,">="&MAX($AA75,$C$5),Donnees!$A$2:$A$2107,"<="&MIN(EOMONTH($AA75,0),$C$6))+($D$14="Oui")*SUMIFS(Donnees!$E$2:$E$2107,Donnees!$A$2:$A$2107,">="&MAX($AA75,$C$5),Donnees!$A$2:$A$2107,"<="&MIN(EOMONTH($AA75,0),$C$6))+($D$15="Oui")*SUMIFS(Donnees!$F$2:$F$2107,Donnees!$A$2:$A$2107,">="&MAX($AA75,$C$5),Donnees!$A$2:$A$2107,"<="&MIN(EOMONTH($AA75,0),$C$6))+($D$16="Oui")*SUMIFS(Donnees!$G$2:$G$2107,Donnees!$A$2:$A$2107,">="&MAX($AA75,$C$5),Donnees!$A$2:$A$2107,"<="&MIN(EOMONTH($AA75,0),$C$6))+($D$17="Oui")*SUMIFS(Donnees!$H$2:$H$2107,Donnees!$A$2:$A$2107,">="&MAX($AA75,$C$5),Donnees!$A$2:$A$2107,"<="&MIN(EOMONTH($AA75,0),$C$6))+($D$18="Oui")*SUMIFS(Donnees!$I$2:$I$2107,Donnees!$A$2:$A$2107,">="&MAX($AA75,$C$5),Donnees!$A$2:$A$2107,"<="&MIN(EOMONTH($AA75,0),$C$6)),NA()) -> #N/A
AA76: 43617 | AB76: =IF(AND(EOMONTH($AA76,0)>=$C$5,$AA76<=$C$6),($D$11="Oui")*SUMIFS(Donnees!$B$2:$B$2107,Donnees!$A$2:$A$2107,">="&MAX($AA76,$C$5),Donnees!$A$2:$A$2107,"<="&MIN(EOMONTH($AA76,0),$C$6))+($D$12="Oui")*SUMIFS(Donnees!$C$2:$C$2107,Donnees!$A$2:$A$2107,">="&MAX($AA76,$C$5),Donnees!$A$2:$A$2107,"<="&MIN(EOMONTH($AA76,0),$C$6))+($D$13="Oui")*SUMIFS(Donnees!$D$2:$D$2107,Donnees!$A$2:$A$2107,">="&MAX($AA76,$C$5),Donnees!$A$2:$A$2107,"<="&MIN(EOMONTH($AA76,0),$C$6))+($D$14="Oui")*SUMIFS(Donnees!$E$2:$E$2107,Donnees!$A$2:$A$2107,">="&MAX($AA76,$C$5),Donnees!$A$2:$A$2107,"<="&MIN(EOMONTH($AA76,0),$C$6))+($D$15="Oui")*SUMIFS(Donnees!$F$2:$F$2107,Donnees!$A$2:$A$2107,">="&MAX($AA76,$C$5),Donnees!$A$2:$A$2107,"<="&MIN(EOMONTH($AA76,0),$C$6))+($D$16="Oui")*SUMIFS(Donnees!$G$2:$G$2107,Donnees!$A$2:$A$2107,">="&MAX($AA76,$C$5),Donnees!$A$2:$A$2107,"<="&MIN(EOMONTH($AA76,0),$C$6))+($D$17="Oui")*SUMIFS(Donnees!$H$2:$H$2107,Donnees!$A$2:$A$2107,">="&MAX($AA76,$C$5),Donnees!$A$2:$A$2107,"<="&MIN(EOMONTH($AA76,0),$C$6))+($D$18="Oui")*SUMIFS(Donnees!$I$2:$I$2107,Donnees!$A$2:$A$2107,">="&MAX($AA76,$C$5),Donnees!$A$2:$A$2107,"<="&MIN(EOMONTH($AA76,0),$C$6)),NA()) -> #N/A
AA77: 43647 | AB77: =IF(AND(EOMONTH($AA77,0)>=$C$5,$AA77<=$C$6),($D$11="Oui")*SUMIFS(Donnees!$B$2:$B$2107,Donnees!$A$2:$A$2107,">="&MAX($AA77,$C$5),Donnees!$A$2:$A$2107,"<="&MIN(EOMONTH($AA77,0),$C$6))+($D$12="Oui")*SUMIFS(Donnees!$C$2:$C$2107,Donnees!$A$2:$A$2107,">="&MAX($AA77,$C$5),Donnees!$A$2:$A$2107,"<="&MIN(EOMONTH($AA77,0),$C$6))+($D$13="Oui")*SUMIFS(Donnees!$D$2:$D$2107,Donnees!$A$2:$A$2107,">="&MAX($AA77,$C$5),Donnees!$A$2:$A$2107,"<="&MIN(EOMONTH($AA77,0),$C$6))+($D$14="Oui")*SUMIFS(Donnees!$E$2:$E$2107,Donnees!$A$2:$A$2107,">="&MAX($AA77,$C$5),Donnees!$A$2:$A$2107,"<="&MIN(EOMONTH($AA77,0),$C$6))+($D$15="Oui")*SUMIFS(Donnees!$F$2:$F$2107,Donnees!$A$2:$A$2107,">="&MAX($AA77,$C$5),Donnees!$A$2:$A$2107,"<="&MIN(EOMONTH($AA77,0),$C$6))+($D$16="Oui")*SUMIFS(Donnees!$G$2:$G$2107,Donnees!$A$2:$A$2107,">="&MAX($AA77,$C$5),Donnees!$A$2:$A$2107,"<="&MIN(EOMONTH($AA77,0),$C$6))+($D$17="Oui")*SUMIFS(Donnees!$H$2:$H$2107,Donnees!$A$2:$A$2107,">="&MAX($AA77,$C$5),Donnees!$A$2:$A$2107,"<="&MIN(EOMONTH($AA77,0),$C$6))+($D$18="Oui")*SUMIFS(Donnees!$I$2:$I$2107,Donnees!$A$2:$A$2107,">="&MAX($AA77,$C$5),Donnees!$A$2:$A$2107,"<="&MIN(EOMONTH($AA77,0),$C$6)),NA()) -> #N/A
AA78: 43678 | AB78: =IF(AND(EOMONTH($AA78,0)>=$C$5,$AA78<=$C$6),($D$11="Oui")*SUMIFS(Donnees!$B$2:$B$2107,Donnees!$A$2:$A$2107,">="&MAX($AA78,$C$5),Donnees!$A$2:$A$2107,"<="&MIN(EOMONTH($AA78,0),$C$6))+($D$12="Oui")*SUMIFS(Donnees!$C$2:$C$2107,Donnees!$A$2:$A$2107,">="&MAX($AA78,$C$5),Donnees!$A$2:$A$2107,"<="&MIN(EOMONTH($AA78,0),$C$6))+($D$13="Oui")*SUMIFS(Donnees!$D$2:$D$2107,Donnees!$A$2:$A$2107,">="&MAX($AA78,$C$5),Donnees!$A$2:$A$2107,"<="&MIN(EOMONTH($AA78,0),$C$6))+($D$14="Oui")*SUMIFS(Donnees!$E$2:$E$2107,Donnees!$A$2:$A$2107,">="&MAX($AA78,$C$5),Donnees!$A$2:$A$2107,"<="&MIN(EOMONTH($AA78,0),$C$6))+($D$15="Oui")*SUMIFS(Donnees!$F$2:$F$2107,Donnees!$A$2:$A$2107,">="&MAX($AA78,$C$5),Donnees!$A$2:$A$2107,"<="&MIN(EOMONTH($AA78,0),$C$6))+($D$16="Oui")*SUMIFS(Donnees!$G$2:$G$2107,Donnees!$A$2:$A$2107,">="&MAX($AA78,$C$5),Donnees!$A$2:$A$2107,"<="&MIN(EOMONTH($AA78,0),$C$6))+($D$17="Oui")*SUMIFS(Donnees!$H$2:$H$2107,Donnees!$A$2:$A$2107,">="&MAX($AA78,$C$5),Donnees!$A$2:$A$2107,"<="&MIN(EOMONTH($AA78,0),$C$6))+($D$18="Oui")*SUMIFS(Donnees!$I$2:$I$2107,Donnees!$A$2:$A$2107,">="&MAX($AA78,$C$5),Donnees!$A$2:$A$2107,"<="&MIN(EOMONTH($AA78,0),$C$6)),NA()) -> #N/A
AA79: 43709 | AB79: =IF(AND(EOMONTH($AA79,0)>=$C$5,$AA79<=$C$6),($D$11="Oui")*SUMIFS(Donnees!$B$2:$B$2107,Donnees!$A$2:$A$2107,">="&MAX($AA79,$C$5),Donnees!$A$2:$A$2107,"<="&MIN(EOMONTH($AA79,0),$C$6))+($D$12="Oui")*SUMIFS(Donnees!$C$2:$C$2107,Donnees!$A$2:$A$2107,">="&MAX($AA79,$C$5),Donnees!$A$2:$A$2107,"<="&MIN(EOMONTH($AA79,0),$C$6))+($D$13="Oui")*SUMIFS(Donnees!$D$2:$D$2107,Donnees!$A$2:$A$2107,">="&MAX($AA79,$C$5),Donnees!$A$2:$A$2107,"<="&MIN(EOMONTH($AA79,0),$C$6))+($D$14="Oui")*SUMIFS(Donnees!$E$2:$E$2107,Donnees!$A$2:$A$2107,">="&MAX($AA79,$C$5),Donnees!$A$2:$A$2107,"<="&MIN(EOMONTH($AA79,0),$C$6))+($D$15="Oui")*SUMIFS(Donnees!$F$2:$F$2107,Donnees!$A$2:$A$2107,">="&MAX($AA79,$C$5),Donnees!$A$2:$A$2107,"<="&MIN(EOMONTH($AA79,0),$C$6))+($D$16="Oui")*SUMIFS(Donnees!$G$2:$G$2107,Donnees!$A$2:$A$2107,">="&MAX($AA79,$C$5),Donnees!$A$2:$A$2107,"<="&MIN(EOMONTH($AA79,0),$C$6))+($D$17="Oui")*SUMIFS(Donnees!$H$2:$H$2107,Donnees!$A$2:$A$2107,">="&MAX($AA79,$C$5),Donnees!$A$2:$A$2107,"<="&MIN(EOMONTH($AA79,0),$C$6))+($D$18="Oui")*SUMIFS(Donnees!$I$2:$I$2107,Donnees!$A$2:$A$2107,">="&MAX($AA79,$C$5),Donnees!$A$2:$A$2107,"<="&MIN(EOMONTH($AA79,0),$C$6)),NA()) -> 1824.8037
AA80: 43739 | AB80: =IF(AND(EOMONTH($AA80,0)>=$C$5,$AA80<=$C$6),($D$11="Oui")*SUMIFS(Donnees!$B$2:$B$2107,Donnees!$A$2:$A$2107,">="&MAX($AA80,$C$5),Donnees!$A$2:$A$2107,"<="&MIN(EOMONTH($AA80,0),$C$6))+($D$12="Oui")*SUMIFS(Donnees!$C$2:$C$2107,Donnees!$A$2:$A$2107,">="&MAX($AA80,$C$5),Donnees!$A$2:$A$2107,"<="&MIN(EOMONTH($AA80,0),$C$6))+($D$13="Oui")*SUMIFS(Donnees!$D$2:$D$2107,Donnees!$A$2:$A$2107,">="&MAX($AA80,$C$5),Donnees!$A$2:$A$2107,"<="&MIN(EOMONTH($AA80,0),$C$6))+($D$14="Oui")*SUMIFS(Donnees!$E$2:$E$2107,Donnees!$A$2:$A$2107,">="&MAX($AA80,$C$5),Donnees!$A$2:$A$2107,"<="&MIN(EOMONTH($AA80,0),$C$6))+($D$15="Oui")*SUMIFS(Donnees!$F$2:$F$2107,Donnees!$A$2:$A$2107,">="&MAX($AA80,$C$5),Donnees!$A$2:$A$2107,"<="&MIN(EOMONTH($AA80,0),$C$6))+($D$16="Oui")*SUMIFS(Donnees!$G$2:$G$2107,Donnees!$A$2:$A$2107,">="&MAX($AA80,$C$5),Donnees!$A$2:$A$2107,"<="&MIN(EOMONTH($AA80,0),$C$6))+($D$17="Oui")*SUMIFS(Donnees!$H$2:$H$2107,Donnees!$A$2:$A$2107,">="&MAX($AA80,$C$5),Donnees!$A$2:$A$2107,"<="&MIN(EOMONTH($AA80,0),$C$6))+($D$18="Oui")*SUMIFS(Donnees!$I$2:$I$2107,Donnees!$A$2:$A$2107,">="&MAX($AA80,$C$5),Donnees!$A$2:$A$2107,"<="&MIN(EOMONTH($AA80,0),$C$6)),NA()) -> #N/A

Sheet Stats
B2: Statistiques descriptives (mois complets uniquement)
B4: Groupe ATC | C4: Libellé | D4: Total | E4: Part du volume | F4: Moyenne par jour | G4: Médiane par jour | H4: Écart-type | I4: Coef. de variation | J4: Jours sans vente | K4: Évolution annuelle moyenne | L4: Mois de pic | M4: Indice du pic | N4: Mois creux | O4: Jour le plus fort
B5: M01AB | C5: Anti-inflammatoires (type diclofénac) | D5: 10679.625 | E5: 0.083026536 | F5: 5.0903837 | G5: 4.99 | H5: 2.71279 | I5: 0.53292447 | J5: 14 | K5: 0.056114242 | L5: Août | M5: 107 | N5: Juin | O5: Samedi
B6: M01AE | C6: Anti-inflammatoires (type ibuprofène) | D6: 8293.549 | E6: 0.064476482 | F6: 3.9530739 | G6: 3.675 | H6: 2.1190956 | I6: 0.53606274 | J6: 10 | K6: 0.025176825 | L6: Janv. | M6: 118 | N6: Juin | O6: Dimanche
B7: N02BA | C7: Antalgiques salicylés (type aspirine) | D7: 8169.0097 | E7: 0.063508276 | F7: 3.8937129 | G7: 3.5 | H7: 2.3428604 | I7: 0.60170343 | J7: 54 | K7: -0.085300816 | L7: Févr. | M7: 121 | N7: Sept. | O7: Mardi
B8: N02BE | C8: Antalgiques (type paracétamol) | D8: 63856.431 | E8: 0.49643862 | F8: 30.436812 | G8: 27 | H8: 15.838967 | I8: 0.52038851 | J8: 0 | K8: 0.053854108 | L8: Janv. | M8: 143 | N8: Juil. | O8: Dimanche
B9: N05B | C9: Anxiolytiques | D9: 18527.008 | E9: 0.1440344 | F9: 8.8307952 | G9: 8 | H9: 5.5320401 | I9: 0.62644869 | J9: 18 | K9: -0.067219566 | L9: Janv. | M9: 116 | N9: Mai | O9: Mercredi
B10: N05C | C10: Hypnotiques et sédatifs | D10: 1242 | E10: 0.0096556722 | F10: 0.59199237 | G10: 0 | H10: 1.0959555 | I10: 1.8513001 | J10: 1432 | K10: -0.030687979 | L10: Janv. | M10: 127 | N10: Avr. | O10: Vendredi
B11: R03 | C11: Asthme et BPCO | D11: 11708.083 | E11: 0.091022073 | F11: 5.5805926 | G11: 4 | H11: 6.4921552 | I11: 1.1633451 | J11: 471 | K11: 0.211559 | L11: Déc. | M11: 148 | N11: Juil. | O11: Lundi
B12: R06 | C12: Antihistaminiques | D12: 6153.35 | E12: 0.047837947 | F12: 2.93296 | G12: 2 | H12: 2.4203131 | I12: 0.82521177 | J12: 241 | K12: 0.10450179 | L12: Mai | M12: 176 | N12: Déc. | O12: Samedi
B14: Indice par mois (100 = mois moyen du groupe)
B15: Groupe | C15: Janv. | D15: Févr. | E15: Mars | F15: Avr. | G15: Mai | H15: Juin | I15: Juil. | J15: Août | K15: Sept. | L15: Oct. | M15: Nov. | N15: Déc.
B16: Anti-inflammatoires (type diclofénac) (M01AB) | C16: 104 | D16: 97 | E16: 97 | F16: 103 | G16: 96 | H16: 93 | I16: 102 | J16: 107 | K16: 98 | L16: 97 | M16: 103 | N16: 103
B17: Anti-inflammatoires (type ibuprofène) (M01AE) | C17: 118 | D17: 118 | E17: 98 | F17: 94 | G17: 94 | H17: 90 | I17: 95 | J17: 92 | K17: 100 | L17: 98 | M17: 96 | N17: 106
B18: Antalgiques salicylés (type aspirine) (N02BA) | C18: 115 | D18: 121 | E18: 102 | F18: 97 | G18: 96 | H18: 96 | I18: 89 | J18: 89 | K18: 86 | L18: 104 | M18: 107 | N18: 98
B19: Antalgiques (type paracétamol) (N02BE) | C19: 143 | D19: 118 | E19: 97 | F19: 87 | G19: 75 | H19: 67 | I19: 63 | J19: 67 | K19: 104 | L19: 138 | M19: 106 | N19: 135
B20: Anxiolytiques (N05B) | C20: 116 | D20: 100 | E20: 93 | F20: 91 | G20: 85 | H20: 89 | I20: 94 | J20: 103 | K20: 104 | L20: 106 | M20: 105 | N20: 113
B21: Hypnotiques et sédatifs (N05C) | C21: 127 | D21: 91 | E21: 105 | F21: 81 | G21: 103 | H21: 99 | I21: 81 | J21: 103 | K21: 88 | L21: 85 | M21: 114 | N21: 123
B22: Asthme et BPCO (R03) | C22: 126 | D22: 120 | E22: 111 | F22: 103 | G22: 89 | H22: 77 | I22: 52 | J22: 55 | K22: 78 | L22: 130 | M22: 110 | N22: 148
B23: Antihistaminiques (R06) | C23: 56 | D23: 58 | E23: 111 | F23: 171 | G23: 176 | H23: 154 | I23: 117 | J23: 94 | K23: 89 | L23: 69 | M23: 55 | N23: 51
B25: Indice par jour de semaine (100 = jour moyen du groupe)
B26: Groupe | C26: Lundi | D26: Mardi | E26: Mercredi | F26: Jeudi | G26: Vendredi | H26: Samedi | I26: Dimanche
B27: Anti-inflammatoires (type diclofénac) (M01AB) | C27: 101 | D27: 100 | E27: 93 | F27: 90 | G27: 95 | H27: 114 | I27: 107
B28: Anti-inflammatoires (type ibuprofène) (M01AE) | C28: 96 | D28: 91 | E28: 94 | F28: 93 | G28: 95 | H28: 111 | I28: 119
B29: Antalgiques salicylés (type aspirine) (N02BA) | C29: 101 | D29: 110 | E29: 95 | F29: 96 | G29: 100 | H29: 108 | I29: 90
B30: Antalgiques (type paracétamol) (N02BE) | C30: 98 | D30: 94 | E30: 93 | F30: 94 | G30: 96 | H30: 112 | I30: 114
B31: Anxiolytiques (N05B) | C31: 105 | D31: 108 | E31: 114 | F31: 99 | G31: 112 | H31: 97 | I31: 65
B32: Hypnotiques et sédatifs (N05C) | C32: 104 | D32: 119 | E32: 112 | F32: 90 | G32: 129 | H32: 92 | I32: 53
B33: Asthme et BPCO (R03) | C33: 108 | D33: 97 | E33: 99 | F33: 97 | G33: 104 | H33: 101 | I33: 94
B34: Antihistaminiques (R06) | C34: 99 | D34: 105 | E34: 92 | F34: 90 | G34: 95 | H34: 112 | I34: 106
B36: Indice par heure (100 = heure moyenne du groupe, export horaire)
B37: Groupe | C37: 0h | D37: 1h | E37: 2h | F37: 3h | G37: 4h | H37: 5h | I37: 6h | J37: 7h | K37: 8h | L37: 9h | M37: 10h | N37: 11h | O37: 12h | P37: 13h | Q37: 14h | R37: 15h | S37: 16h | T37: 17h | U37: 18h | V37: 19h | W37: 20h | X37: 21h | Y37: 22h | Z37: 23h
B38: Anti-inflammatoires (type diclofénac) (M01AB) | C38: 0 | D38: 0 | E38: 0 | F38: 0 | G38: 0 | H38: 0 | I38: 0 | J38: 7 | K38: 129 | L38: 170 | M38: 197 | N38: 222 | O38: 211 | P38: 184 | Q38: 194 | R38: 145 | S38: 134 | T38: 140 | U38: 167 | V38: 199 | W38: 181 | X38: 119 | Y38: 1 | Z38: 0
B39: Anti-inflammatoires (type ibuprofène) (M01AE) | C39: 0 | D39: 0 | E39: 0 | F39: 0 | G39: 0 | H39: 0 | I39: 0 | J39: 11 | K39: 97 | L39: 133 | M39: 162 | N39: 195 | O39: 188 | P39: 162 | Q39: 171 | R39: 148 | S39: 154 | T39: 174 | U39: 193 | V39: 236 | W39: 243 | X39: 133 | Y39: 1 | Z39: 0
B40: Antalgiques salicylés (type aspirine) (N02BA) | C40: 0 | D40: 0 | E40: 0 | F40: 0 | G40: 0 | H40: 0 | I40: 0 | J40: 7 | K40: 129 | L40: 210 | M40: 250 | N40: 249 | O40: 214 | P40: 198 | Q40: 154 | R40: 137 | S40: 119 | T40: 135 | U40: 182 | V40: 170 | W40: 161 | X40: 83 | Y40: 1 | Z40: 0
B41: Antalgiques (type paracétamol) (N02BE) | C41: 0 | D41: 0 | E41: 0 | F41: 0 | G41: 0 | H41: 0 | I41: 0 | J41: 13 | K41: 105 | L41: 138 | M41: 159 | N41: 186 | O41: 194 | P41: 165 | Q41: 159 | R41: 161 | S41: 160 | T41: 166 | U41: 198 | V41: 228 | W41: 228 | X41: 138 | Y41: 1 | Z41: 0
B42: Anxiolytiques (N05B) | C42: 0 | D42: 0 | E42: 0 | F42: 0 | G42: 0 | H42: 0 | I42: 0 | J42: 8 | K42: 136 | L42: 188 | M42: 238 | N42: 261 | O42: 245 | P42: 223 | Q42: 174 | R42: 151 | S42: 138 | T42: 131 | U42: 149 | V42: 151 | W42: 132 | X42: 74 | Y42: 1 | Z42: 0
B43: Hypnotiques et sédatifs (N05C) | C43: 0 | D43: 0 | E43: 0 | F43: 0 | G43: 0 | H43: 0 | I43: 0 | J43: 8 | K43: 97 | L43: 126 | M43: 180 | N43: 187 | O43: 230 | P43: 267 | Q43: 184 | R43: 213 | S43: 170 | T43: 153 | U43: 195 | V43: 166 | W43: 168 | X43: 58 | Y43: 0 | Z43: 0
B44: Asthme et BPCO (R03) | C44: 0 | D44: 0 | E44: 0 | F44: 0 | G44: 0 | H44: 0 | I44: 0 | J44: 12 | K44: 138 | L44: 151 | M44: 176 | N44: 169 | O44: 139 | P44: 159 | Q44: 153 | R44: 139 | S44: 122 | T44: 167 | U44: 231 | V44: 254 | W44: 253 | X44: 134 | Y44: 2 | Z44: 0
B45: Antihistaminiques (R06) | C45: 0 | D45: 0 | E45: 0 | F45: 0 | G45: 0 | H45: 0 | I45: 0 | J45: 7 | K45: 109 | L45: 146 | M45: 184 | N45: 190 | O45: 196 | P45: 186 | Q45: 158 | R45: 147 | S45: 126 | T45: 136 | U45: 202 | V45: 227 | W45: 237 | X45: 148 | Y45: 0 | Z45: 0

Sheet Prevision
B2: Tendance, saisonnalité et prévision de octobre 2019
B4: 1. Y a-t-il une tendance, une saisonnalité, ou les deux ?
B5: Tests sur la vente moyenne par jour de chaque mois complet. Une p-value sous 0.05 signale un effet peu compatible avec le hasard.
B6: Libellé | C6: Code | D6: Pente par an (% du niveau moyen) | E6: p-value tendance | F6: p-value saisonnalité | G6: Part de variance expliquée (R²) | H6: Structure détectée
B7: Anti-inflammatoires (type diclofénac) | C7: M01AB | D7: 0.032900268 | E7: 0.002241682 | F7: 0.88041365 | G7: 0.22296515 | H7: Tendance seule
B8: Anti-inflammatoires (type ibuprofène) | C8: M01AE | D8: 0.0068628692 | E8: 0.53543158 | F8: 0.023879635 | G8: 0.30708442 | H8: Saisonnalité seule
B9: Antalgiques salicylés (type aspirine) | C9: N02BA | D9: -0.085416011 | E9: 2.7013948e-12 | F9: 0.0074505347 | G9: 0.68129452 | H9: Tendance + saisonnalité
B10: Antalgiques (type paracétamol) | C10: N02BE | D10: 0.014052542 | E10: 0.35959679 | F10: 1.3131042e-10 | G10: 0.68788976 | H10: Saisonnalité seule
B11: Anxiolytiques | C11: N05B | D11: -0.054246939 | E11: 0.0095548071 | F11: 0.75870243 | G11: 0.20827282 | H11: Tendance seule
B12: Hypnotiques et sédatifs | C12: N05C | D12: 0.010024037 | E12: 0.74342036 | F12: 0.65925705 | G12: 0.13340185 | H12: Ni l'une ni l'autre
B13: Asthme et BPCO | C13: R03 | D13: 0.14471755 | E13: 2.0010966e-09 | F13: 5.9872102e-08 | G13: 0.69300433 | H13: Tendance + saisonnalité
B14: Antihistaminiques | C14: R06 | D14: 0.078410358 | E14: 1.8611972e-05 | F14: 1.535349e-16 | G14: 0.82752227 | H14: Tendance + saisonnalité
B16: 2. Quelle famille prévoit le mieux ? Test sur 24 mois (10/2017 à 09/2019), erreur moyenne en % des ventes du mois
B17: Libellé | C17: Code | D17: Meilleure régression | E17: Erreur régression | F17: Meilleur lissage | G17: Erreur lissage | H17: Meilleure naïve | I17: Erreur naïve | J17: Gain du meilleur modèle sur la naïve | K17: Méthode retenue | L17: Erreur de la méthode retenue | M17: Prévisible ?
B18: Anti-inflammatoires (type diclofénac) | C18: M01AB | D18: Saisonnalité seule | E18: 0.085043546 | F18: Lissage simple | G18: 0.077427846 | H18: Naïve : dernier mois | I18: 0.10039915 | J18: 0.2287998 | K18: Lissage simple | L18: 0.077427846 | M18: Oui
B19: Anti-inflammatoires (type ibuprofène) | C19: M01AE | D19: Saisonnalité seule | E19: 0.1255741 | F19: Holt-Winters sans tendance (saison) | G19: 0.13259145 | H19: Naïve : même mois an dernier | I19: 0.14262107 | J19: 0.11952634 | K19: Saisonnalité seule | L19: 0.1255741 | M19: Oui
B20: Antalgiques salicylés (type aspirine) | C20: N02BA | D20: Tendance seule | E20: 0.11706356 | F20: Holt-Winters sans tendance (saison) | G20: 0.10768598 | H20: Naïve : dernier mois | I20: 0.10276064 | J20: -0.047930208 | K20: Naïve : dernier mois | L20: 0.10276064 | M20: Oui, une règle simple suffit
B21: Antalgiques (type paracétamol) | C21: N02BE | D21: Saisonnalité seule | E21: 0.12119717 | F21: Holt-Winters sans tendance (saison) | G21: 0.14611828 | H21: Naïve : dernier mois | I21: 0.22756715 | J21: 0.46742236 | K21: Saisonnalité seule | L21: 0.12119717 | M21: Oui
B22: Anxiolytiques | C22: N05B | D22: Saisonnalité seule | E22: 0.20446856 | F22: Lissage simple | G22: 0.12503006 | H22: Naïve : dernier mois | I22: 0.14464235 | J22: 0.1355916 | K22: Lissage simple | L22: 0.12503006 | M22: Oui
B23: Hypnotiques et sédatifs | C23: N05C | D23: Tendance seule | E23: 0.30728861 | F23: Lissage simple | G23: 0.26844666 | H23: Naïve : dernier mois | I23: 0.38329764 | J23: 0.29963917 | K23: Lissage simple | L23: 0.26844666 | M23: Non
B24: Asthme et BPCO | C24: R03 | D24: Tendance + saisonnalité | E24: 0.23228208 | F24: Lissage simple | G24: 0.23761207 | H24: Naïve : dernier mois | I24: 0.24823629 | J24: 0.064270235 | K24: Naïve : dernier mois | L24: 0.24823629 | M24: Non
B25: Antihistaminiques | C25: R06 | D25: Tendance + saisonnalité | E25: 0.19895372 | F25: Holt-Winters (tendance + saison) | G25: 0.2022541 | H25: Naïve : même mois an dernier | I25: 0.26519947 | J25: 0.24979593 | K25: Tendance + saisonnalité | L25: 0.19895372 | M25: Oui
B26: Chaque mois de test est prévu sans utiliser sa valeur, avec un modèle réajusté sur les seuls mois antérieurs.
B28: Détail : erreur de chaque méthode (en vert, la plus petite de la ligne)
B29: Libellé | C29: Code | D29: Tendance seule | E29: Saisonnalité seule | F29: Tendance + saisonnalité | G29: Lissage simple | H29: Lissage de Holt (tendance) | I29: Holt-Winters sans tendance (saison) | J29: Holt-Winters (tendance + saison) | K29: Naïve : même mois an dernier | L29: Naïve : dernier mois
B30: Anti-inflammatoires (type diclofénac) | C30: M01AB | D30: 0.10665743 | E30: 0.085043546 | F30: 0.10514432 | G30: 0.077427846 | H30: 0.078163376 | I30: 0.078980266 | J30: 0.079993031 | K30: 0.1026969 | L30: 0.10039915
B31: Anti-inflammatoires (type ibuprofène) | C31: M01AE | D31: 0.16516614 | E31: 0.1255741 | F31: 0.15396543 | G31: 0.1527494 | H31: 0.15614837 | I31: 0.13259145 | J31: 0.14198177 | K31: 0.14262107 | L31: 0.15970925
B32: Antalgiques salicylés (type aspirine) | C32: N02BA | D32: 0.11706356 | E32: 0.29908807 | F32: 0.12610635 | G32: 0.11544441 | H32: 0.12360654 | I32: 0.10768598 | J32: 0.11589252 | K32: 0.14834454 | L32: 0.10276064
B33: Antalgiques (type paracétamol) | C33: N02BE | D33: 0.27899064 | E33: 0.12119717 | F33: 0.14004801 | G33: 0.23668661 | H33: 0.23770592 | I33: 0.14611828 | J33: 0.14727205 | K33: 0.23303442 | L33: 0.22756715
B34: Anxiolytiques | C34: N05B | D34: 0.22003584 | E34: 0.20446856 | F34: 0.26484391 | G34: 0.12503006 | H34: 0.12702672 | I34: 0.17194606 | J34: 0.17456622 | K34: 0.22211896 | L34: 0.14464235
B35: Hypnotiques et sédatifs | C35: N05C | D35: 0.30728861 | E35: 0.36832189 | F35: 0.39311049 | G35: 0.26844666 | H35: 0.27623918 | I35: 0.34369174 | J35: 0.36971992 | K35: 0.53104925 | L35: 0.38329764
B36: Asthme et BPCO | C36: R03 | D36: 0.3287035 | E36: 0.3428966 | F36: 0.23228208 | G36: 0.23761207 | H36: 0.23894117 | I36: 0.24640317 | J36: 0.25013495 | K36: 0.30533725 | L36: 0.24823629
B37: Antihistaminiques | C37: R06 | D37: 0.39831406 | E37: 0.23530814 | F37: 0.19895372 | G37: 0.28860613 | H37: 0.29093034 | I37: 0.20365646 | J37: 0.2022541 | K37: 0.26519947 | L37: 0.28992504
B39: 3. Prévision pour octobre 2019 (quantités, unité du logiciel de caisse)
B40: Libellé | C40: Code | D40: Prévision | E40: Fourchette basse | F40: Fourchette haute | G40: Même mois, année précédente | H40: Méthode | I40: Prévisible ?
B41: Anti-inflammatoires (type diclofénac) | C41: M01AB | D41: 171.51839 | E41: 159.25074 | F41: 193.55554 | G41: 144.71 | H41: Lissage simple | I41: Oui
B42: Anti-inflammatoires (type ibuprofène) | C42: M01AE | D42: 120.3442 | E42: 99.48868 | F42: 133.59981 | G42: 129.4 | H42: Saisonnalité seule | I42: Oui
B43: Antalgiques salicylés (type aspirine) | C43: N02BA | D43: 93.5 | E43: 83.065 | F43: 107.585 | G43: 76.05 | H43: Naïve : dernier mois | I43: Oui, une règle simple suffit
B44: Antalgiques (type paracétamol) | C44: N02BE | D44: 1315.1333 | E44: 1160.4324 | F44: 1433.3698 | G44: 1129.275 | H44: Saisonnalité seule | I44: Oui
B45: Anxiolytiques | C45: N05B | D45: 235.39333 | E45: 177.49733 | F45: 285.37 | G45: 287 | H45: Lissage simple | I45: Oui
B46: Hypnotiques et sédatifs | C46: N05C | D46: 21.578279 | E46: 15.663967 | F46: 28.751877 | G46: 25 | H46: Lissage simple | I46: Non
B47: Asthme et BPCO | C47: R03 | D47: 121.41667 | E47: 56.616667 | F47: 206.80417 | G47: 327 | H47: Naïve : dernier mois | I47: Non
B48: Antihistaminiques | C48: R06 | D48: 83.064541 | E48: 58.758224 | F48: 128.22755 | G48: 76.9 | H48: Tendance + saisonnalité | I48: Oui
B49: Fourchette : 8 mois sur 10, l'écart constaté pendant le test est resté dans cet intervalle. Pour un groupe marqué Non, le chiffre est donné à titre indicatif.
B51: Méthode. Toutes les méthodes travaillent sur la vente moyenne par jour de chaque mois, pour neutraliser la longueur du mois. Régressions linéaires : tendance seule (droite dans le temps), saisonnalité seule (un niveau par mois de l'année), tendance + saisonnalité ; tous les mois de l'historique pèsent autant. Lissages exponentiels : simple (niveau), Holt (niveau + tendance), Holt-Winters sans tendance (niveau + saison), Holt-Winters (niveau + tendance + saison), composantes additives ; les mois récents pèsent plus que les anciens. Tableau 1 : tendance testée par un test de Student sur la pente, saisonnalité par un test de Fisher sur les 11 écarts mensuels, chacune une fois l'autre prise en compte. Ces tests supposent des mois indépendants, ce qui est rarement vrai pour des ventes : les p-values sont optimistes et le tableau 2 fait foi. Tableau 2 : le meilleur modèle est retenu s'il réduit l'erreur d'au moins 10% par rapport à la meilleure naïve, sinon la naïve est gardée. Un groupe est jugé prévisible si l'erreur de la méthode retenue reste sous 20%. Les seuils se règlent en haut de main.py.
B77: Réel, meilleure régression et meilleur lissage sur les mois de test

Sheet Etat_donnees
B2: État des données
B4: Contrôle de chaque export
B5: Export | C5: Lignes | D5: Doublons (lignes complètes) | E5: Dates invalides | F5: Dates en double | G5: Début | H5: Fin | I5: Dates distinctes | J5: Dates attendues | K5: Dates manquantes | L5: Valeurs vides | M5: Valeurs négatives
B6: Hourly | C6: 50532 | D6: 0 | E6: 0 | F6: 0 | G6: 41641.333 | H6: 43746.792 | I6: 50532 | J6: 50532 | K6: 0 | L6: 0 | M6: 0
B7: Daily | C7: 2106 | D7: 0 | E7: 0 | F7: 0 | G7: 41641 | H7: 43746 | I7: 2106 | J7: 2106 | K7: 0 | L7: 0 | M7: 0
B8: Weekly | C8: 302 | D8: 0 | E8: 0 | F8: 0 | G8: 41644 | H8: 43751 | I8: 302 | J8: 302 | K8: 0 | L8: 0 | M8: 0
B9: Monthly | C9: 70 | D9: 0 | E9: 0 | F9: 0 | G9: 41670 | H9: 43769 | I9: 70 | J9: 70 | K9: 0 | L9: 0 | M9: 0
B11: Cohérence des totaux entre exports
B12: Groupe ATC | C12: Libellé | D12: Hourly | E12: Daily | F12: Weekly | G12: Monthly | H12: Écart max vs Daily (%)
B13: M01AB | C13: Anti-inflammatoires (type diclofénac) | D13: 10724 | E13: 10724 | F13: 10724 | G13: 10824.7 | H13: 0.94
B14: M01AE | C14: Anti-inflammatoires (type ibuprofène) | D14: 8330.85 | E14: 8330.85 | F14: 8330.85 | G14: 8455.04 | H14: 1.49
B15: N02BA | C15: Antalgiques salicylés (type aspirine) | D15: 8189.66 | E15: 8189.66 | F15: 8189.66 | G15: 8286.06 | H15: 1.18
B16: N02BE | C16: Antalgiques (type paracétamol) | D16: 64151.58 | E16: 64151.58 | F16: 64151.58 | G16: 65208.01 | H16: 1.65
B17: N05B | C17: Anxiolytiques | D17: 18613.01 | E17: 18613.01 | F17: 18613.01 | G17: 18793.11 | H17: 0.97
B18: N05C | C18: Hypnotiques et sédatifs | D18: 1249 | E18: 1249 | F18: 1249 | G18: 1286.38 | H18: 2.99
B19: R03 | C19: Asthme et BPCO | D19: 11745.08 | E19: 11745.08 | F19: 11745.08 | G19: 12093.25 | H19: 2.96
B20: R06 | C20: Antihistaminiques | D20: 6164.48 | E20: 6164.48 | F20: 6164.48 | G20: 6192.29 | H20: 0.45
B21: Un écart faible est attendu si les exports ne s'arrêtent pas à la même date.
B23: Quel export sert à quoi
B24: Export | C24: Utilisation
B25: Daily | C25: Outil de sélection, statistiques par groupe, saisonnalité, jour de semaine, prévision.
B26: Hourly | C26: Profil par heure de la journée uniquement.
B27: Weekly | C27: Contrôle de cohérence uniquement (non utilisé dans les statistiques).
B28: Monthly | C28: Contrôle de cohérence uniquement (les mois sont recalculés à partir du Daily).
B30: Corrections et mises à l'écart
B31: Export | C31: Traitement
B32: Daily | C32: Mois incomplet écarté des statistiques : données du 01/10/2019 au 08/10/2019 (conservées dans l'outil de sélection).

Sheet Dictionnaire
A1: Code ATC | B1: Libellé
A2: M01AB | B2: Anti-inflammatoires (type diclofénac)
A3: M01AE | B3: Anti-inflammatoires (type ibuprofène)
A4: N02BA | B4: Antalgiques salicylés (type aspirine)
A5: N02BE | B5: Antalgiques (type paracétamol)
A6: N05B | B6: Anxiolytiques
A7: N05C | B7: Hypnotiques et sédatifs
A8: R03 | B8: Asthme et BPCO
A9: R06 | B9: Antihistaminiques
A11: Libellés à vérifier avec la classification ATC officielle.

Sheet Mensuel
A1: Mois | B1: M01AB | C1: M01AE | D1: N02BA | E1: N02BE | F1: N05B | G1: N05C | H1: R03 | I1: R06
A2: 41640 | B2: 132.02 | C2: 99.75 | D2: 154.6 | E2: 915.03 | F2: 360 | G2: 30 | H2: 115 | I2: 52.2
A3: 41671 | B3: 133.32 | C3: 126.05 | D3: 177 | E3: 1001.9 | F3: 347 | G3: 31 | H3: 122 | I3: 36.2
A4: 41699 | B4: 137.44 | C4: 92.95 | D4: 147.655 | E4: 779.275 | F4: 232 | G4: 20 | H4: 112 | I4: 85.4
A5: 41730 | B5: 119.44 | C5: 91.475 | D5: 127.15 | E5: 718.5 | F5: 216 | G5: 18 | H5: 97 | I5: 77.7
A6: 41760 | B6: 103.46 | C6: 125.933 | D6: 135.1 | E6: 640.78 | F6: 273 | G6: 23 | H6: 108 | I6: 127.7
A7: 41791 | B7: 112.07 | C7: 94.71 | D7: 122.9 | E7: 548.225 | F7: 323 | G7: 23 | H7: 57 | I7: 109.3
A8: 41821 | B8: 117.06 | C8: 95.01 | D8: 129.3 | E8: 491.9 | F8: 348 | G8: 21 | H8: 61 | I8: 69.1
A9: 41852 | B9: 124.79 | C9: 99.78 | D9: 123.8 | E9: 547.35 | F9: 420 | G9: 29 | H9: 37 | I9: 70.8
A10: 41883 | B10: 108.78 | C10: 109.094 | D10: 112.1 | E10: 887.82 | F10: 399 | G10: 14 | H10: 115 | I10: 58.8
A11: 41913 | B11: 98.42 | C11: 109.231 | D11: 142.6 | E11: 1046.415 | F11: 430 | G11: 19 | H11: 157 | I11: 46.8
A12: 41944 | B12: 138.08 | C12: 100.86 | D12: 142.7 | E12: 723.8 | F12: 489 | G12: 19 | H12: 112 | I12: 45.2
A13: 41974 | B13: 143.9 | C13: 130.302 | D13: 113.324 | E13: 1036.16 | F13: 525 | G13: 26 | H13: 163 | I13: 35.4
... A70: 43709 | B70: 161.07 | C70: 111.437 | D70: 93.5 | E70: 984.48 | F70: 227.8 | G70: 16 | H70: 121.41667 | I70: 109.1

Sheet Backtest
A1: Mois | B1: Groupe ATC | C1: Réel | D1: Tendance seule | E1: Saisonnalité seule | F1: Tendance + saisonnalité | G1: Lissage simple | H1: Lissage de Holt (tendance) | I1: Holt-Winters sans tendance (saison) | J1: Holt-Winters (tendance + saison) | K1: Naïve : même mois an dernier | L1: Naïve : dernier mois
A2: 43009 | B2: M01AB | C2: 140.97 | D2: 181.55397 | E2: 160.33 | F2: 187.68229 | G2: 150.38522 | H2: 151.15844 | I2: 150.18332 | J2: 151.15689 | K2: 186.76 | L2: 138.33
A3: 43040 | B3: M01AB | C3: 163.85 | D3: 173.35065 | E3: 149.23556 | F3: 173.1941 | G3: 140.89617 | H3: 141.41212 | I3: 133.99525 | J3: 134.72935 | K3: 166.84667 | L3: 140.97
A4: 43070 | B4: M01AB | C4: 162.51 | D4: 179.28493 | E4: 161.56667 | F4: 185.81564 | G4: 157.33908 | H4: 158.31304 | I4: 161.77835 | J4: 163.18669 | K4: 172.66 | L4: 163.85
A5: 43101 | B5: M01AB | C5: 151.44 | D5: 178.85235 | E5: 161.86 | F5: 190.71461 | G5: 159.94683 | H5: 161.00136 | I5: 169.39383 | J5: 171.03638 | K5: 184.53 | L5: 162.51
A6: 43132 | B6: M01AB | C6: 128.36 | D6: 160.35613 | E6: 142.20789 | F6: 165.54136 | G6: 140.66778 | H6: 141.54175 | I6: 139.65851 | J6: 140.55992 | K6: 151.985 | L6: 151.44
A7: 43160 | B7: M01AB | C7: 146.16 | D7: 175.55861 | E7: 153.2425 | F7: 176.13563 | G7: 149.06137 | H7: 149.76354 | I7: 143.28484 | J7: 143.90361 | K7: 162.85 | L7: 128.36
A8: 43191 | B8: M01AB | C8: 171.02 | D8: 168.41118 | E8: 151.125 | F8: 171.34573 | G8: 142.85335 | H8: 143.42488 | I8: 142.70476 | J8: 143.29948 | K8: 160.61 | L8: 146.16
A9: 43221 | B9: M01AB | C9: 160.52 | D9: 174.9378 | E9: 144.625 | F9: 165.49871 | G9: 161.54652 | H9: 162.5728 | I9: 150.81894 | J9: 151.81939 | K9: 143.66 | L9: 171.02
A10: 43252 | B10: M01AB | C10: 141.18 | D10: 168.93007 | E10: 138.985 | F10: 158.90195 | G10: 155.84912 | H10: 156.87541 | I10: 149.60915 | J10: 150.68558 | K10: 122.33 | L10: 160.52
A11: 43282 | B11: M01AB | C11: 150.18 | D11: 173.11818 | E11: 159.37333 | F11: 178.93681 | G11: 153.93636 | H11: 154.84188 | I11: 164.99001 | J11: 166.11305 | K11: 150.295 | L11: 141.18
A12: 43313 | B12: M01AB | C12: 140 | D12: 172.0732 | E12: 171.94 | F12: 189.98996 | G12: 152.174 | H12: 152.97125 | I12: 169.22578 | J12: 170.18313 | K12: 170.15 | L12: 150.18
A13: 43344 | B13: M01AB | C13: 153.52 | D13: 164.86532 | E13: 146.5725 | F13: 161.62134 | G13: 141.67606 | H13: 142.19924 | I13: 127.75427 | J13: 128.07818 | K13: 138.33 | L13: 140
... A193: 43709 | B193: R06 | C193: 109.1 | D193: 108.4457 | E193: 70.82 | F193: 90.741674 | G193: 94.16129 | H193: 94.81271 | I193: 86.694038 | J193: 90.741686 | K193: 88.1 | L193: 97.3

Sheet Donnees
A1: Date | B1: M01AB | C1: M01AE | D1: N02BA | E1: N02BE | F1: N05B | G1: N05C | H1: R03 | I1: R06
A2: 41641 | B2: 0 | C2: 3.67 | D2: 3.4 | E2: 32.4 | F2: 7 | G2: 0 | H2: 0 | I2: 2
A3: 41642 | B3: 8 | C3: 4 | D3: 4.4 | E3: 50.6 | F3: 16 | G3: 0 | H3: 20 | I3: 4
A4: 41643 | B4: 2 | C4: 1 | D4: 6.5 | E4: 61.85 | F4: 10 | G4: 0 | H4: 9 | I4: 1
A5: 41644 | B5: 4 | C5: 3 | D5: 7 | E5: 41.1 | F5: 8 | G5: 0 | H5: 3 | I5: 0
A6: 41645 | B6: 5 | C6: 1 | D6: 4.5 | E6: 21.7 | F6: 16 | G6: 2 | H6: 6 | I6: 2
A7: 41646 | B7: 4.33 | C7: 0.66 | D7: 2.5 | E7: 37 | F7: 6 | G7: 0 | H7: 3 | I7: 4
A8: 41647 | B8: 5.33 | C8: 3 | D8: 10.5 | E8: 26.4 | F8: 19 | G8: 1 | H8: 10 | I8: 0
A9: 41648 | B9: 7 | C9: 1.68 | D9: 8 | E9: 25 | F9: 16 | G9: 0 | H9: 3 | I9: 2
A10: 41649 | B10: 5 | C10: 2 | D10: 2 | E10: 53.3 | F10: 15 | G10: 2 | H10: 0 | I10: 2
A11: 41650 | B11: 5 | C11: 4.34 | D11: 10.4 | E11: 52.3 | F11: 14 | G11: 0 | H11: 1 | I11: 0.2
A12: 41651 | B12: 2 | C12: 0.66 | D12: 2.5 | E12: 12 | F12: 8 | G12: 0 | H12: 1 | I12: 1
A13: 41652 | B13: 7.34 | C13: 7.66 | D13: 6.2 | E13: 52 | F13: 9 | G13: 0 | H13: 7 | I13: 1
... A2107: 43746 | B2107: 0.33 | C2107: 1.73 | D2107: 0.5 | E2107: 44.3 | F2107: 20 | G2107: 2 | H2107: 2 | I2107: 0
